Workbook

Sheet Cover
A5: Corporate valuation suite · Shell plc and BP p.l.c.
A6: Built 12 Oct 2026 by export_excel.py from the Python engine. Base case. Not investment advice.
A8: Model check status | B8: =Checks!F42 -> ALL PASS
A10: Contents
A11: Inputs | B11: Forecast and valuation assumptions for Shell (edit the blue cells)
A12: Forecast | B12: Integrated income statement, cash flow and balance sheet, 2026–2035
A13: DCF | B13: WACC, unlevered free cash flow, terminal value, equity bridge, sensitivity grid
A14: LBO | B14: Carve-out buyout of Shell's Marketing division: sources and uses, debt schedule, returns
A15: Merger | B15: Shell acquires BP: consideration, funding, purchase price allocation, EPS accretion
A16: Portfolio | B16: 13-asset sterling portfolio: expected returns, covariance, portfolio statistics
A17: Checks | B17: Every key result reconciled to the Python engine
A18: History | B18: Shell FY2021–FY2025 reported figures from the 20-F
A20: Colour code
A21: Blue text: hard-coded input
A22: Black text: formula
A23: Green text: link to another sheet
A24: Yellow fill: key assumption
A26: Calculation
A27: Interest on average balances makes the Forecast and LBO sheets circular. Iterative calculation is saved with the workbook; if Excel warns about circular references, enable File › Options › Formulas › Enable iterative calculation.

Sheet Inputs
A1: Shell plc · forecast and valuation inputs
A2: Base case. Blue cells are inputs; change them and every sheet recalculates. Defaults are calibrated from Shell's own history by the Python engine (model/three_statement.py).
A4: Annual drivers | B4: Unit | C4: 2026 | D4: 2027 | E4: 2028 | F4: 2029 | G4: 2030 | H4: 2031 | I4: 2032 | J4: 2033 | K4: 2034 | L4: 2035
A5: Revenue growth | B5: % | C5: -0.01 | D5: 0.01 | E5: 0.02 | F5: 0.02 | G5: 0.02 | H5: 0.019 | I5: 0.018 | J5: 0.017 | K5: 0.016 | L5: 0.015
A6: Operating EBIT margin | B6: % | C6: 0.10938983 | D6: 0.10938983 | E6: 0.10938983 | F6: 0.10938983 | G6: 0.10938983 | H6: 0.10938983 | I6: 0.10938983 | J6: 0.10938983 | K6: 0.10938983 | L6: 0.10938983
A7: D&A excl. impairments | B7: % rev | C7: 0.083054188 | D7: 0.083054188 | E7: 0.083054188 | F7: 0.083054188 | G7: 0.083054188 | H7: 0.083054188 | I7: 0.083054188 | J7: 0.083054188 | K7: 0.083054188 | L7: 0.083054188
A8: Capital expenditure | B8: % rev | C8: 0.070992858 | D8: 0.070992858 | E8: 0.070992858 | F8: 0.070992858 | G8: 0.070992858 | H8: 0.070992858 | I8: 0.070992858 | J8: 0.070992858 | K8: 0.070992858 | L8: 0.070992858
A9: New leases = lease principal repaid | B9: % rev | C9: 0.019712536 | D9: 0.019712536 | E9: 0.019712536 | F9: 0.019712536 | G9: 0.019712536 | H9: 0.019712536 | I9: 0.019712536 | J9: 0.019712536 | K9: 0.019712536 | L9: 0.019712536
A10: Tax rate on pre-tax profit ex JV | B10: % | C10: 0.38444881 | D10: 0.38167103 | E10: 0.37889325 | F10: 0.37611548 | G10: 0.3733377 | H10: 0.37055992 | I10: 0.36778214 | J10: 0.36500436 | K10: 0.36222659 | L10: 0.35944881
A11: Share of JV profit | B11: % rev | C11: 0.0094515242 | D11: 0.0094515242 | E11: 0.0094515242 | F11: 0.0094515242 | G11: 0.0094515242 | H11: 0.0094515242 | I11: 0.0094515242 | J11: 0.0094515242 | K11: 0.0094515242 | L11: 0.0094515242
A12: Dividends | B12: USD m | C12: 8963.76 | D12: 9322.3104 | E12: 9695.2028 | F12: 10083.011 | G12: 10486.331 | H12: 10748.49 | I12: 11017.202 | J12: 11292.632 | K12: 11574.948 | L12: 11864.321
A13: Buyback target (flexes to protect cash floor) | B13: USD m | C13: 13879 | D13: 13879 | E13: 13879 | F13: 13879 | G13: 13879 | H13: 13879 | I13: 13879 | J13: 13879 | K13: 13879 | L13: 13879
A14: Net new borrowing | B14: USD m | C14: 0 | D14: 0 | E14: 0 | F14: 0 | G14: 0 | H14: 0 | I14: 0 | J14: 0 | K14: 0 | L14: 0
A16: Balance-sheet and financing drivers
A17: Receivables | B17: % rev | C17: 0.16710131
A18: Inventories | B18: % rev | C18: 0.083241534
A19: Payables | B19: % rev | C19: 0.21645946
A20: Interest rate on borrowings + leases | B20: % | C20: 0.04466608
A21: Interest rate on cash | B21: % | C21: 0.03
A22: Minority (NCI) income, fixed | B22: USD m | C22: 328.66667
A23: Minimum cash | B23: % rev | C23: 0.09
A24: Circularity switch: 1 = interest on average balances, 0 = opening balances | B24: 1/0 | C24: 1
A26: Valuation inputs
A27: Risk-free rate (US 10y, blend of spot and 1-year average) | B27: % | C27: 0.048206906
A28: Equity risk premium | B28: % | C28: 0.05
A29: Beta (5y weekly vs FTSE 100, Blume-adjusted) | B29: x | C29: 0.972
A30: Credit spread over risk-free | B30: % | C30: 0.009
A31: Tax rate on interest / provisions | B31: % | C31: 0.25
A32: Terminal growth | B32: % | C32: 0.015
A33: Exit EV/EBITDA (cross-check) | B33: x | C33: 5
A34: Shares outstanding | B34: m | C34: 5691.4747
A35: Share price | B35: GBp | C35: 3836
A36: GBP/USD | B36: USD per GBP | C36: 1.3207946
A37: Valuation date | B37: date | C37: 46305

Sheet Forecast
A1: Shell plc · integrated three-statement forecast
A2: USD millions. Column B is the FY2025 opening balance sheet (from History); C–L are forecasts. Interest is on average balances, so the sheet is circular: iterative calculation is switched on.
B4: 2025A | C4: 2026E | D4: 2027E | E4: 2028E | F4: 2029E | G4: 2030E | H4: 2031E | I4: 2032E | J4: 2033E | K4: 2034E | L4: 2035E
A5: Income statement
A6: Revenue | B6: =History!$F$5 -> 266886 | C6: =B6*(1+Inputs!C$5) -> 264217.14 | D6: =C6*(1+Inputs!D$5) -> 266859.31 | E6: =D6*(1+Inputs!E$5) -> 272196.5 | F6: =E6*(1+Inputs!F$5) -> 277640.43 | G6: =F6*(1+Inputs!G$5) -> 283193.24 | H6: =G6*(1+Inputs!H$5) -> 288573.91 | I6: =H6*(1+Inputs!I$5) -> 293768.24 | J6: =I6*(1+Inputs!J$5) -> 298762.3 | ... L6: =K6*(1+Inputs!L$5) -> 308095.63
A7: Operating EBIT | C7: =C6*Inputs!C$6 -> 28902.669 | D7: =D6*Inputs!D$6 -> 29191.695 | E7: =E6*Inputs!E$6 -> 29775.529 | F7: =F6*Inputs!F$6 -> 30371.04 | G7: =G6*Inputs!G$6 -> 30978.461 | H7: =H6*Inputs!H$6 -> 31567.051 | I7: =I6*Inputs!I$6 -> 32135.258 | J7: =J6*Inputs!J$6 -> 32681.558 | ... L7: =L6*Inputs!L$6 -> 33702.53
A8: D&A | C8: =C6*Inputs!C$7 -> 21944.34 | D8: =D6*Inputs!D$7 -> 22163.783 | E8: =E6*Inputs!E$7 -> 22607.059 | F8: =F6*Inputs!F$7 -> 23059.2 | G8: =G6*Inputs!G$7 -> 23520.384 | H8: =H6*Inputs!H$7 -> 23967.272 | I8: =I6*Inputs!I$7 -> 24398.682 | J8: =J6*Inputs!J$7 -> 24813.46 | ... L8: =L6*Inputs!L$7 -> 25588.633
A9: EBITDA | C9: =C7+C8 -> 50847.009 | D9: =D7+D8 -> 51355.479 | E9: =E7+E8 -> 52382.588 | F9: =F7+F8 -> 53430.24 | G9: =G7+G8 -> 54498.845 | H9: =H7+H8 -> 55534.323 | I9: =I7+I8 -> 56533.941 | J9: =J7+J8 -> 57495.018 | ... L9: =L7+L8 -> 59291.162
A10: Interest expense | C10: =IFERROR(Inputs!$C$20*(IF(Inputs!$C$24=1,((B46+B47)+(B46+B47+Inputs!C$14+C33-C34))/2,(B46+B47))+B48),0) -> 4671 | D10: =IFERROR(Inputs!$C$20*(IF(Inputs!$C$24=1,((C46+C47)+(C46+C47+Inputs!D$14+D33-D34))/2,(C46+C47))+C48),0) -> 4671 | E10: =IFERROR(Inputs!$C$20*(IF(Inputs!$C$24=1,((D46+D47)+(D46+D47+Inputs!E$14+E33-E34))/2,(D46+D47))+D48),0) -> 4671 | F10: =IFERROR(Inputs!$C$20*(IF(Inputs!$C$24=1,((E46+E47)+(E46+E47+Inputs!F$14+F33-F34))/2,(E46+E47))+E48),0) -> 4671 | G10: =IFERROR(Inputs!$C$20*(IF(Inputs!$C$24=1,((F46+F47)+(F46+F47+Inputs!G$14+G33-G34))/2,(F46+F47))+F48),0) -> 4671 | H10: =IFERROR(Inputs!$C$20*(IF(Inputs!$C$24=1,((G46+G47)+(G46+G47+Inputs!H$14+H33-H34))/2,(G46+G47))+G48),0) -> 4671 | I10: =IFERROR(Inputs!$C$20*(IF(Inputs!$C$24=1,((H46+H47)+(H46+H47+Inputs!I$14+I33-I34))/2,(H46+H47))+H48),0) -> 4671 | J10: =IFERROR(Inputs!$C$20*(IF(Inputs!$C$24=1,((I46+I47)+(I46+I47+Inputs!J$14+J33-J34))/2,(I46+I47))+I48),0) -> 4671 | ... L10: =IFERROR(Inputs!$C$20*(IF(Inputs!$C$24=1,((K46+K47)+(K46+K47+Inputs!L$14+L33-L34))/2,(K46+K47))+K48),0) -> 4671
A11: Interest income | C11: =IFERROR(Inputs!$C$21*IF(Inputs!$C$24=1,(B41+C41)/2,B41),0) -> 809.93314 | D11: =IFERROR(Inputs!$C$21*IF(Inputs!$C$24=1,(C41+D41)/2,C41),0) -> 716.95321 | E11: =IFERROR(Inputs!$C$21*IF(Inputs!$C$24=1,(D41+E41)/2,D41),0) -> 727.72534 | F11: =IFERROR(Inputs!$C$21*IF(Inputs!$C$24=1,(E41+F41)/2,E41),0) -> 742.27985 | G11: =IFERROR(Inputs!$C$21*IF(Inputs!$C$24=1,(F41+G41)/2,F41),0) -> 757.12545 | H11: =IFERROR(Inputs!$C$21*IF(Inputs!$C$24=1,(G41+H41)/2,G41),0) -> 771.88564 | I11: =IFERROR(Inputs!$C$21*IF(Inputs!$C$24=1,(H41+I41)/2,H41),0) -> 786.1619 | J11: =IFERROR(Inputs!$C$21*IF(Inputs!$C$24=1,(I41+J41)/2,I41),0) -> 799.91622 | ... L11: =IFERROR(Inputs!$C$21*IF(Inputs!$C$24=1,(K41+L41)/2,K41),0) -> 825.71147
A12: Pre-tax profit ex JV | C12: =C7-C10+C11 -> 25041.602 | D12: =D7-D10+D11 -> 25237.649 | E12: =E7-E10+E11 -> 25832.255 | F12: =F7-F10+F11 -> 26442.32 | G12: =G7-G10+G11 -> 27064.586 | H12: =H7-H10+H11 -> 27667.937 | I12: =I7-I10+I11 -> 28250.42 | J12: =J7-J10+J11 -> 28810.474 | ... L12: =L7-L10+L11 -> 29857.241
A13: Tax | C13: =C12*Inputs!C$10 -> 9627.214 | D13: =D12*Inputs!D$10 -> 9632.4794 | E13: =E12*Inputs!E$10 -> 9787.667 | F13: =F12*Inputs!F$10 -> 9945.3657 | G13: =G12*Inputs!G$10 -> 10104.23 | H13: =H12*Inputs!H$10 -> 10252.629 | I13: =I12*Inputs!I$10 -> 10390 | J13: =J12*Inputs!J$10 -> 10515.949 | ... L13: =L12*Inputs!L$10 -> 10732.15
A14: Share of JV profit | C14: =C6*Inputs!C$11 -> 2497.2547 | D14: =D6*Inputs!D$11 -> 2522.2272 | E14: =E6*Inputs!E$11 -> 2572.6718 | F14: =F6*Inputs!F$11 -> 2624.1252 | G14: =G6*Inputs!G$11 -> 2676.6077 | H14: =H6*Inputs!H$11 -> 2727.4633 | I14: =I6*Inputs!I$11 -> 2776.5576 | J14: =J6*Inputs!J$11 -> 2823.7591 | ... L14: =L6*Inputs!L$11 -> 2911.9733
A15: Net income | C15: =C12-C13+C14 -> 17911.643 | D15: =D12-D13+D14 -> 18127.397 | E15: =E12-E13+E14 -> 18617.259 | F15: =F12-F13+F14 -> 19121.079 | G15: =G12-G13+G14 -> 19636.964 | H15: =H12-H13+H14 -> 20142.772 | I15: =I12-I13+I14 -> 20636.978 | J15: =J12-J13+J14 -> 21118.284 | ... L15: =L12-L13+L14 -> 22037.065
A16: Minorities | C16: =Inputs!$C$22 -> 328.66667 | D16: =Inputs!$C$22 -> 328.66667 | E16: =Inputs!$C$22 -> 328.66667 | F16: =Inputs!$C$22 -> 328.66667 | G16: =Inputs!$C$22 -> 328.66667 | H16: =Inputs!$C$22 -> 328.66667 | I16: =Inputs!$C$22 -> 328.66667 | J16: =Inputs!$C$22 -> 328.66667 | ... L16: =Inputs!$C$22 -> 328.66667
A17: Net income to shareholders | C17: =C15-C16 -> 17582.976 | D17: =D15-D16 -> 17798.73 | E17: =E15-E16 -> 18288.593 | F17: =F15-F16 -> 18792.413 | G17: =G15-G16 -> 19308.297 | H17: =H15-H16 -> 19814.105 | I17: =I15-I16 -> 20308.311 | J17: =J15-J16 -> 20789.618 | ... L17: =L15-L16 -> 21708.398
A19: Working capital
A20: Receivables | B20: =History!$F$22 -> 44597 | C20: =C6*Inputs!$C$17 -> 44151.03 | D20: =D6*Inputs!$C$17 -> 44592.54 | E20: =E6*Inputs!$C$17 -> 45484.391 | F20: =F6*Inputs!$C$17 -> 46394.079 | G20: =G6*Inputs!$C$17 -> 47321.961 | H20: =H6*Inputs!$C$17 -> 48221.078 | I20: =I6*Inputs!$C$17 -> 49089.057 | J20: =J6*Inputs!$C$17 -> 49923.571 | ... L20: =L6*Inputs!$C$17 -> 51483.183
A21: Inventories | B21: =History!$F$21 -> 22216 | C21: =C6*Inputs!$C$18 -> 21993.84 | D21: =D6*Inputs!$C$18 -> 22213.778 | E21: =E6*Inputs!$C$18 -> 22658.054 | F21: =F6*Inputs!$C$18 -> 23111.215 | G21: =G6*Inputs!$C$18 -> 23573.439 | H21: =H6*Inputs!$C$18 -> 24021.335 | I21: =I6*Inputs!$C$18 -> 24453.719 | J21: =J6*Inputs!$C$18 -> 24869.432 | ... L21: =L6*Inputs!$C$18 -> 25646.353
A22: Payables | B22: =History!$F$28 -> 57770 | C22: =C6*Inputs!$C$19 -> 57192.3 | D22: =D6*Inputs!$C$19 -> 57764.223 | E22: =E6*Inputs!$C$19 -> 58919.507 | F22: =F6*Inputs!$C$19 -> 60097.898 | G22: =G6*Inputs!$C$19 -> 61299.856 | H22: =H6*Inputs!$C$19 -> 62464.553 | I22: =I6*Inputs!$C$19 -> 63588.915 | J22: =J6*Inputs!$C$19 -> 64669.926 | ... L22: =L6*Inputs!$C$19 -> 66690.215
A23: Increase in working capital | C23: =(C20-B20)+(C21-B21)-(C22-B22) -> -90.43 | D23: =(D20-C20)+(D21-C21)-(D22-C22) -> 89.5257 | E23: =(E20-D20)+(E21-D21)-(E22-D22) -> 180.84191 | F23: =(F20-E20)+(F21-E21)-(F22-E22) -> 184.45875 | G23: =(G20-F20)+(G21-F21)-(G22-F22) -> 188.14793 | H23: =(H20-G20)+(H21-G21)-(H22-G22) -> 182.31534 | I23: =(I20-H20)+(I21-H21)-(I22-H22) -> 176.00147 | J23: =(J20-I20)+(J21-I21)-(J22-I22) -> 169.21564 | ... L23: =(L20-K20)+(L21-K21)-(L22-K22) -> 154.27569
A24: Minimum cash (floor) | C24: =C6*Inputs!$C$23 -> 23779.543 | D24: =D6*Inputs!$C$23 -> 24017.338 | E24: =E6*Inputs!$C$23 -> 24497.685 | F24: =F6*Inputs!$C$23 -> 24987.638 | G24: =G6*Inputs!$C$23 -> 25487.391 | H24: =H6*Inputs!$C$23 -> 25971.652 | I24: =I6*Inputs!$C$23 -> 26439.141 | J24: =J6*Inputs!$C$23 -> 26888.607 | ... L24: =L6*Inputs!$C$23 -> 27728.607
A26: Cash flow
A27: Cash from operations | C27: =C15+C8-C23 -> 39946.413 | D27: =D15+D8-D23 -> 40201.654 | E27: =E15+E8-E23 -> 41043.477 | F27: =F15+F8-F23 -> 41995.821 | G27: =G15+G8-G23 -> 42969.2 | H27: =H15+H8-H23 -> 43927.728 | I27: =I15+I8-I23 -> 44859.659 | J27: =J15+J8-J23 -> 45762.529 | ... L27: =L15+L8-L23 -> 47471.422
A28: Capital expenditure | C28: =C6*Inputs!C$8 -> 18757.53 | D28: =D6*Inputs!D$8 -> 18945.105 | E28: =E6*Inputs!E$8 -> 19324.007 | F28: =F6*Inputs!F$8 -> 19710.488 | G28: =G6*Inputs!G$8 -> 20104.697 | H28: =H6*Inputs!H$8 -> 20486.687 | I28: =I6*Inputs!I$8 -> 20855.447 | J28: =J6*Inputs!J$8 -> 21209.99 | ... L28: =L6*Inputs!L$8 -> 21872.59
A29: Lease principal / new leases | C29: =C6*Inputs!C$9 -> 5208.39 | D29: =D6*Inputs!D$9 -> 5260.4739 | E29: =E6*Inputs!E$9 -> 5365.6834 | F29: =F6*Inputs!F$9 -> 5472.997 | G29: =G6*Inputs!G$9 -> 5582.457 | H29: =H6*Inputs!H$9 -> 5688.5237 | I29: =I6*Inputs!I$9 -> 5790.9171 | J29: =J6*Inputs!J$9 -> 5889.3627 | ... L29: =L6*Inputs!L$9 -> 6073.3464
A30: Cash from investing | C30: =-C28 -> -18757.53 | D30: =-D28 -> -18945.105 | E30: =-E28 -> -19324.007 | F30: =-F28 -> -19710.488 | G30: =-G28 -> -20104.697 | H30: =-H28 -> -20486.687 | I30: =-I28 -> -20855.447 | J30: =-J28 -> -21209.99 | ... L30: =-L28 -> -21872.59
A31: Cash before buybacks and revolver | C31: =B41+C27+C30+Inputs!C$14-C36-C16-C29 -> 36904.066 | D31: =C41+D27+D30+Inputs!D$14-D36-D16-D29 -> 30124.641 | E31: =D41+E27+E30+Inputs!E$14-E36-E16-E29 -> 30347.254 | F31: =E41+F27+F30+Inputs!F$14-F36-F16-F29 -> 30898.343 | G31: =F41+G27+G30+Inputs!G$14-G36-G16-G29 -> 31454.686 | H31: =G41+H27+H30+Inputs!H$14-H36-H16-H29 -> 32162.753 | I31: =H41+I27+I30+Inputs!I$14-I36-I16-I29 -> 32839.078 | J31: =I41+J27+J30+Inputs!J$14-J36-J16-J29 -> 33481.019 | ... L31: =K41+L27+L30+Inputs!L$14-L36-L16-L29 -> 34651.322
A32: Cash available above the floor | C32: =C31-C24 -> 13124.523 | D32: =D31-D24 -> 6107.3025 | E32: =E31-E24 -> 5849.5696 | F32: =F31-F24 -> 5910.7049 | G32: =G31-G24 -> 5967.2948 | H32: =H31-H24 -> 6191.1011 | I32: =I31-I24 -> 6399.9365 | J32: =J31-J24 -> 6592.4126 | ... L32: =L31-L24 -> 6922.7151
A33: Revolver drawn | C33: =MAX(0,-C32) -> 0 | D33: =MAX(0,-D32) -> 0 | E33: =MAX(0,-E32) -> 0 | F33: =MAX(0,-F32) -> 0 | G33: =MAX(0,-G32) -> 0 | H33: =MAX(0,-H32) -> 0 | I33: =MAX(0,-I32) -> 0 | J33: =MAX(0,-J32) -> 0 | ... L33: =MAX(0,-L32) -> 0
A34: Revolver repaid | C34: =MIN(B47,MAX(0,C32)) -> 0 | D34: =MIN(C47,MAX(0,D32)) -> 0 | E34: =MIN(D47,MAX(0,E32)) -> 0 | F34: =MIN(E47,MAX(0,F32)) -> 0 | G34: =MIN(F47,MAX(0,G32)) -> 0 | H34: =MIN(G47,MAX(0,H32)) -> 0 | I34: =MIN(H47,MAX(0,I32)) -> 0 | J34: =MIN(I47,MAX(0,J32)) -> 0 | ... L34: =MIN(K47,MAX(0,L32)) -> 0
A35: Share buybacks | C35: =MAX(0,MIN(Inputs!C$13,C32-C34)) -> 13124.523 | D35: =MAX(0,MIN(Inputs!D$13,D32-D34)) -> 6107.3025 | E35: =MAX(0,MIN(Inputs!E$13,E32-E34)) -> 5849.5696 | F35: =MAX(0,MIN(Inputs!F$13,F32-F34)) -> 5910.7049 | G35: =MAX(0,MIN(Inputs!G$13,G32-G34)) -> 5967.2948 | H35: =MAX(0,MIN(Inputs!H$13,H32-H34)) -> 6191.1011 | I35: =MAX(0,MIN(Inputs!I$13,I32-I34)) -> 6399.9365 | J35: =MAX(0,MIN(Inputs!J$13,J32-J34)) -> 6592.4126 | ... L35: =MAX(0,MIN(Inputs!L$13,L32-L34)) -> 6922.7151
A36: Dividends | C36: =Inputs!C$12 -> 8963.76 | D36: =Inputs!D$12 -> 9322.3104 | E36: =Inputs!E$12 -> 9695.2028 | F36: =Inputs!F$12 -> 10083.011 | G36: =Inputs!G$12 -> 10486.331 | H36: =Inputs!H$12 -> 10748.49 | I36: =Inputs!I$12 -> 11017.202 | J36: =Inputs!J$12 -> 11292.632 | ... L36: =Inputs!L$12 -> 11864.321
A37: Cash from financing | C37: =Inputs!C$14+C33-C34-C36-C35-C16-C29 -> -27625.34 | D37: =Inputs!D$14+D33-D34-D36-D35-D16-D29 -> -21018.753 | E37: =Inputs!E$14+E33-E34-E36-E35-E16-E29 -> -21239.122 | F37: =Inputs!F$14+F33-F34-F36-F35-F16-F29 -> -21795.38 | G37: =Inputs!G$14+G33-G34-G36-G35-G16-G29 -> -22364.75 | H37: =Inputs!H$14+H33-H34-H36-H35-H16-H29 -> -22956.781 | I37: =Inputs!I$14+I33-I34-I36-I35-I16-I29 -> -23536.722 | J37: =Inputs!J$14+J33-J34-J36-J35-J16-J29 -> -24103.074 | ... L37: =Inputs!L$14+L33-L34-L36-L35-L16-L29 -> -25189.05
A38: Net change in cash | C38: =C27+C30+C37 -> -6436.4574 | D38: =D27+D30+D37 -> 237.79543 | E38: =E27+E30+E37 -> 480.34676 | F38: =F27+F30+F37 -> 489.9537 | G38: =G27+G30+G37 -> 499.75277 | H38: =H27+H30+H37 -> 484.26043 | I38: =I27+I30+I37 -> 467.48973 | J38: =J27+J30+J37 -> 449.4654 | ... L38: =L27+L30+L37 -> 409.78237
A40: Balance sheet
A41: Cash | B41: =History!$F$20 -> 30216 | C41: =B41+C38 -> 23779.543 | D41: =C41+D38 -> 24017.338 | E41: =D41+E38 -> 24497.685 | F41: =E41+F38 -> 24987.638 | G41: =F41+G38 -> 25487.391 | H41: =G41+H38 -> 25971.652 | I41: =H41+I38 -> 26439.141 | J41: =I41+J38 -> 26888.607 | ... L41: =K41+L38 -> 27728.607
A42: Fixed assets incl. right-of-use | B42: =History!$F$23+History!$F$25 -> 196087 | C42: =B42+C28+C29-C8 -> 198108.58 | D42: =C42+D28+D29-D8 -> 200150.38 | E42: =D42+E28+E29-E8 -> 202233.01 | F42: =E42+F28+F29-F8 -> 204357.29 | G42: =F42+G28+G29-G8 -> 206524.06 | H42: =G42+H28+H29-H8 -> 208732 | I42: =H42+I28+I29-I8 -> 210979.68 | J42: =I42+J28+J29-J8 -> 213265.57 | ... L42: =K42+L28+L29-L8 -> 217945.34
A43: Goodwill | B43: =History!$F$24 -> 15662 | C43: =B43 -> 15662 | D43: =C43 -> 15662 | E43: =D43 -> 15662 | F43: =E43 -> 15662 | G43: =F43 -> 15662 | H43: =G43 -> 15662 | I43: =H43 -> 15662 | J43: =I43 -> 15662 | ... L43: =K43 -> 15662
A44: Other assets (plug, held flat) | B44: =History!$F$18-B41-B20-B21-B42-B43 -> 61572 | C44: =B44 -> 61572 | D44: =C44 -> 61572 | E44: =D44 -> 61572 | F44: =E44 -> 61572 | G44: =F44 -> 61572 | H44: =G44 -> 61572 | I44: =H44 -> 61572 | J44: =I44 -> 61572 | ... L44: =K44 -> 61572
A45: Total assets | B45: =B41+B20+B21+B42+B43+B44 -> 370350 | C45: =C41+C20+C21+C42+C43+C44 -> 365266.99 | D45: =D41+D20+D21+D42+D43+D44 -> 368208.03 | E45: =E41+E20+E21+E42+E43+E44 -> 372107.14 | F45: =F41+F20+F21+F42+F43+F44 -> 376084.22 | G45: =G41+G20+G21+G42+G43+G44 -> 380140.85 | H45: =H41+H20+H21+H42+H43+H44 -> 384180.06 | I45: =I41+I20+I21+I42+I43+I44 -> 388195.6 | ... L45: =L41+L20+L21+L42+L43+L44 -> 400037.49
A46: Borrowings | B46: =History!$F$29+History!$F$30 -> 75643 | C46: =B46+Inputs!C$14 -> 75643 | D46: =C46+Inputs!D$14 -> 75643 | E46: =D46+Inputs!E$14 -> 75643 | F46: =E46+Inputs!F$14 -> 75643 | G46: =F46+Inputs!G$14 -> 75643 | H46: =G46+Inputs!H$14 -> 75643 | I46: =H46+Inputs!I$14 -> 75643 | J46: =I46+Inputs!J$14 -> 75643 | ... L46: =K46+Inputs!L$14 -> 75643
A47: Revolver | B47: 0 | C47: =B47+C33-C34 -> 0 | D47: =C47+D33-D34 -> 0 | E47: =D47+E33-E34 -> 0 | F47: =E47+F33-F34 -> 0 | G47: =F47+G33-G34 -> 0 | H47: =G47+H33-H34 -> 0 | I47: =H47+I33-I34 -> 0 | J47: =I47+J33-J34 -> 0 | ... L47: =K47+L33-L34 -> 0
A48: Lease liabilities | B48: =History!$F$31 -> 28933 | C48: =B48 -> 28933 | D48: =C48 -> 28933 | E48: =D48 -> 28933 | F48: =E48 -> 28933 | G48: =F48 -> 28933 | H48: =G48 -> 28933 | I48: =H48 -> 28933 | J48: =I48 -> 28933 | ... L48: =K48 -> 28933
A49: Other liabilities (plug, held flat) | B49: =History!$F$26-B22-B46-B48 -> 32685 | C49: =B49 -> 32685 | D49: =C49 -> 32685 | E49: =D49 -> 32685 | F49: =E49 -> 32685 | G49: =F49 -> 32685 | H49: =G49 -> 32685 | I49: =H49 -> 32685 | J49: =I49 -> 32685 | ... L49: =K49 -> 32685
A50: Total liabilities | B50: =B22+B46+B47+B48+B49 -> 195031 | C50: =C22+C46+C47+C48+C49 -> 194453.3 | D50: =D22+D46+D47+D48+D49 -> 195025.22 | E50: =E22+E46+E47+E48+E49 -> 196180.51 | F50: =F22+F46+F47+F48+F49 -> 197358.9 | G50: =G22+G46+G47+G48+G49 -> 198560.86 | H50: =H22+H46+H47+H48+H49 -> 199725.55 | I50: =I22+I46+I47+I48+I49 -> 200849.91 | ... L50: =L22+L46+L47+L48+L49 -> 203951.21
A51: Shareholders’ equity | B51: =History!$F$33 -> 174392 | C51: =B51+C17-C36-C35 -> 169886.69 | D51: =C51+D17-D36-D35 -> 172255.81 | E51: =D51+E17-E36-E35 -> 174999.63 | F51: =E51+F17-F36-F35 -> 177798.33 | G51: =F51+G17-G36-G35 -> 180653 | H51: =G51+H17-H36-H35 -> 183527.51 | I51: =H51+I17-I36-I35 -> 186418.68 | J51: =I51+J17-J36-J35 -> 189323.26 | ... L51: =K51+L17-L36-L35 -> 195159.27
A52: Minorities | B52: =History!$F$34 -> 927 | C52: =B52 -> 927 | D52: =C52 -> 927 | E52: =D52 -> 927 | F52: =E52 -> 927 | G52: =F52 -> 927 | H52: =G52 -> 927 | I52: =H52 -> 927 | J52: =I52 -> 927 | ... L52: =K52 -> 927
A53: Total equity | B53: =B51+B52 -> 175319 | C53: =C51+C52 -> 170813.69 | D53: =D51+D52 -> 173182.81 | E53: =E51+E52 -> 175926.63 | F53: =F51+F52 -> 178725.33 | G53: =G51+G52 -> 181580 | H53: =H51+H52 -> 184454.51 | I53: =I51+I52 -> 187345.68 | ... L53: =L51+L52 -> 196086.27
A54: Balance check (must be 0) | B54: =B45-B50-B53 -> 0 | C54: =C45-C50-C53 -> 0 | D54: =D45-D50-D53 -> 0 | E54: =E45-E50-E53 -> 0 | F54: =F45-F50-F53 -> 0 | G54: =G45-G50-G53 -> 0 | H54: =H45-H50-H53 -> 0 | I54: =I45-I50-I53 -> 0 | ... L54: =L45-L50-L53 -> 0
A56: Free cash flow and credit
A57: Unlevered free cash flow | C57: =C7*(1-Inputs!C$10)+C8-C28-C29-C23 -> 15859.922 | D57: =D7*(1-Inputs!D$10)+D8-D28-D29-D23 -> 15918.749 | E57: =E7*(1-Inputs!E$10)+E8-E28-E29-E23 -> 16230.309 | F57: =F7*(1-Inputs!F$10)+F8-F28-F29-F23 -> 16639.279 | G57: =G7*(1-Inputs!G$10)+G8-G28-G29-G23 -> 17058.116 | H57: =H7*(1-Inputs!H$10)+H8-H28-H29-H23 -> 17479.313 | I57: =I7*(1-Inputs!I$10)+I8-I28-I29-I23 -> 17892.801 | J57: =J7*(1-Inputs!J$10)+J8-J28-J29-J23 -> 18297.539 | ... L57: =L7*(1-Inputs!L$10)+L8-L28-L29-L23 -> 19076.616
A58: Net debt incl. leases | C58: =C46+C47+C48-C41 -> 80796.457 | D58: =D46+D47+D48-D41 -> 80558.662 | E58: =E46+E47+E48-E41 -> 80078.315 | F58: =F46+F47+F48-F41 -> 79588.362 | G58: =G46+G47+G48-G41 -> 79088.609 | H58: =H46+H47+H48-H41 -> 78604.348 | I58: =I46+I47+I48-I41 -> 78136.859 | J58: =J46+J47+J48-J41 -> 77687.393 | ... L58: =L46+L47+L48-L41 -> 76847.393
A59: Net debt / EBITDA | C59: =IF(C9<>0,C58/C9,0) -> 1.589011 | D59: =IF(D9<>0,D58/D9,0) -> 1.5686479 | E59: =IF(E9<>0,E58/E9,0) -> 1.5287201 | F59: =IF(F9<>0,F58/F9,0) -> 1.4895752 | G59: =IF(G9<>0,G58/G9,0) -> 1.4511979 | H59: =IF(H9<>0,H58/H9,0) -> 1.4154192 | I59: =IF(I9<>0,I58/I9,0) -> 1.382123 | J59: =IF(J9<>0,J58/J9,0) -> 1.3512022 | ... L59: =IF(L9<>0,L58/L9,0) -> 1.296102

Sheet DCF
A1: Shell plc · discounted cash flow
A2: USD millions unless stated. Mid-year discounting from 31 Dec 2025; value rolled forward to the valuation date.
A4: Cost of capital
A5: Cost of equity = risk-free + beta × ERP | B5: =Inputs!$C$27+Inputs!$C$29*Inputs!$C$28 -> 0.096806906
A6: After-tax cost of debt = (risk-free + spread) × (1 − tax) | B6: =(Inputs!$C$27+Inputs!$C$30)*(1-Inputs!$C$31) -> 0.042905179
A7: Market capitalisation (USD m) | B7: =Inputs!$C$34*Inputs!$C$35/100*Inputs!$C$36 -> 288362.44
A8: Borrowings + leases at book (USD m) | B8: =History!$F$29+History!$F$30+History!$F$31 -> 104576
A9: WACC | B9: =(B7*B5+B8*B6)/(B7+B8) -> 0.082461588
A11: Cash flows
C12: 2026E | D12: 2027E | E12: 2028E | F12: 2029E | G12: 2030E | H12: 2031E | I12: 2032E | J12: 2033E | K12: 2034E | L12: 2035E
A13: Unlevered free cash flow | C13: =Forecast!C57 -> 15859.922 | D13: =Forecast!D57 -> 15918.749 | E13: =Forecast!E57 -> 16230.309 | F13: =Forecast!F57 -> 16639.279 | G13: =Forecast!G57 -> 17058.116 | H13: =Forecast!H57 -> 17479.313 | I13: =Forecast!I57 -> 17892.801 | J13: =Forecast!J57 -> 18297.539 | ... L13: =Forecast!L57 -> 19076.616
A14: Discount period (years, mid-year) | C14: 0.5 | D14: 1.5 | E14: 2.5 | F14: 3.5 | G14: 4.5 | H14: 5.5 | I14: 6.5 | J14: 7.5 | K14: 8.5 | L14: 9.5
A15: Discount factor | C15: =1/(1+$B$9)^C14 -> 0.96115572 | D15: =1/(1+$B$9)^D14 -> 0.88793517 | E15: =1/(1+$B$9)^E14 -> 0.82029255 | F15: =1/(1+$B$9)^F14 -> 0.75780291 | G15: =1/(1+$B$9)^G14 -> 0.70007372 | H15: =1/(1+$B$9)^H14 -> 0.64674233 | I15: =1/(1+$B$9)^I14 -> 0.5974737 | J15: =1/(1+$B$9)^J14 -> 0.55195833 | ... L15: =1/(1+$B$9)^L14 -> 0.47106551
A16: Present value | C16: =C13*C15 -> 15243.855 | D16: =D13*D15 -> 14134.818 | E16: =E13*E15 -> 13313.601 | F16: =F13*F15 -> 12609.294 | G16: =G13*G15 -> 11941.938 | H16: =H13*H15 -> 11304.612 | I16: =I13*I15 -> 10690.478 | J16: =J13*J15 -> 10099.479 | ... L16: =L13*L15 -> 8986.336
A18: Enterprise value to equity value
A19: PV of 10-year cash flows | B19: =SUM(C16:L16) -> 117855.9
A20: Terminal value (Gordon) at 2035 | B20: =L13*(1+Inputs!$C$32)/($B$9-Inputs!$C$32) -> 287019.12
A21: PV of terminal value | B21: =B20/(1+$B$9)^(L14) -> 135204.81
A22: Enterprise value | B22: =B19+B21 -> 253060.71
A23: + Equity-accounted JV stakes (book) | B23: =History!$F$38 -> 27775
A24: − Borrowings | B24: =-(History!$F$29+History!$F$30) -> -75643
A25: − Lease liabilities | B25: =-History!$F$31 -> -28933
A26: + Cash | B26: =History!$F$20 -> 30216
A27: − Minorities | B27: =-History!$F$34 -> -927
A28: − Decommissioning provisions, after tax | B28: =-History!$F$42*(1-Inputs!$C$31) -> -14100.75
A29: − Pension deficit, after tax | B29: =-History!$F$43*(1-Inputs!$C$31) -> -1563
A30: Equity value at 31 Dec 2025 | B30: =SUM(B22:B29) -> 189884.96
A31: Roll-forward (years from 31 Dec 2025) | B31: =(Inputs!$C$37-DATE(2025,12,31))/365 -> 0.77534247
A32: Dividend per share paid in the interim (USD) | B32: =Inputs!C$12/Inputs!$C$34 -> 1.5749451
A33: Value per share (USD) | B33: =B30/Inputs!$C$34*(1+B5)^B31-B32*B31 -> 34.619901
A34: Value per share (pence) | B34: =B33/Inputs!$C$36*100 -> 2621.1419
A35: Upside to market price | B35: =B34/Inputs!$C$35-1 -> -0.31669918
A36: Terminal value share of EV | B36: =B21/B22 -> 0.53427815
A37: Implied exit EV/EBITDA | B37: =B20/Forecast!L9 -> 4.8408416
A39: Cross-check: exit multiple
A40: Terminal value = exit multiple × 2035 EBITDA | B40: =Inputs!$C$33*Forecast!L9 -> 296455.81
A41: PV of terminal value (end-year) | B41: =B40/(1+$B$9)^10 -> 134225.5
A42: Equity value | B42: =B19+B41+SUM(B23:B29) -> 188905.65
A43: Value per share (pence) | B43: =(B42/Inputs!$C$34*(1+B5)^B31-B32*B31)/Inputs!$C$36*100 -> 2607.1469
A45: Sensitivity: value per share (pence), WACC down the side, terminal growth across
A46: WACC \ g | B46: =Inputs!$C$32+-0.01 -> 0.005 | C46: =Inputs!$C$32+-0.005 -> 0.01 | D46: =Inputs!$C$32+0 -> 0.015 | E46: =Inputs!$C$32+0.005 -> 0.02 | F46: =Inputs!$C$32+0.01 -> 0.025
A47: =$B$9+-0.01 -> 0.072461588 | B47: =((SUMPRODUCT($C$13:$L$13/(1+$A47)^$C$14:$L$14)+$L$13*(1+B$46)/($A47-B$46)/(1+$A47)^$L$14+SUM($B$23:$B$29))/Inputs!$C$34*(1+$B$5)^$B$31-$B$32*$B$31)/Inputs!$C$36*100 -> 2851.3717 | C47: =((SUMPRODUCT($C$13:$L$13/(1+$A47)^$C$14:$L$14)+$L$13*(1+C$46)/($A47-C$46)/(1+$A47)^$L$14+SUM($B$23:$B$29))/Inputs!$C$34*(1+$B$5)^$B$31-$B$32*$B$31)/Inputs!$C$36*100 -> 3029.8607 | D47: =((SUMPRODUCT($C$13:$L$13/(1+$A47)^$C$14:$L$14)+$L$13*(1+D$46)/($A47-D$46)/(1+$A47)^$L$14+SUM($B$23:$B$29))/Inputs!$C$34*(1+$B$5)^$B$31-$B$32*$B$31)/Inputs!$C$36*100 -> 3239.412 | E47: =((SUMPRODUCT($C$13:$L$13/(1+$A47)^$C$14:$L$14)+$L$13*(1+E$46)/($A47-E$46)/(1+$A47)^$L$14+SUM($B$23:$B$29))/Inputs!$C$34*(1+$B$5)^$B$31-$B$32*$B$31)/Inputs!$C$36*100 -> 3488.9071 | F47: =((SUMPRODUCT($C$13:$L$13/(1+$A47)^$C$14:$L$14)+$L$13*(1+F$46)/($A47-F$46)/(1+$A47)^$L$14+SUM($B$23:$B$29))/Inputs!$C$34*(1+$B$5)^$B$31-$B$32*$B$31)/Inputs!$C$36*100 -> 3790.97
A48: =$B$9+-0.005 -> 0.077461588 | B48: =((SUMPRODUCT($C$13:$L$13/(1+$A48)^$C$14:$L$14)+$L$13*(1+B$46)/($A48-B$46)/(1+$A48)^$L$14+SUM($B$23:$B$29))/Inputs!$C$34*(1+$B$5)^$B$31-$B$32*$B$31)/Inputs!$C$36*100 -> 2586.0225 | C48: =((SUMPRODUCT($C$13:$L$13/(1+$A48)^$C$14:$L$14)+$L$13*(1+C$46)/($A48-C$46)/(1+$A48)^$L$14+SUM($B$23:$B$29))/Inputs!$C$34*(1+$B$5)^$B$31-$B$32*$B$31)/Inputs!$C$36*100 -> 2733.915 | D48: =((SUMPRODUCT($C$13:$L$13/(1+$A48)^$C$14:$L$14)+$L$13*(1+D$46)/($A48-D$46)/(1+$A48)^$L$14+SUM($B$23:$B$29))/Inputs!$C$34*(1+$B$5)^$B$31-$B$32*$B$31)/Inputs!$C$36*100 -> 2905.4849 | E48: =((SUMPRODUCT($C$13:$L$13/(1+$A48)^$C$14:$L$14)+$L$13*(1+E$46)/($A48-E$46)/(1+$A48)^$L$14+SUM($B$23:$B$29))/Inputs!$C$34*(1+$B$5)^$B$31-$B$32*$B$31)/Inputs!$C$36*100 -> 3106.913 | F48: =((SUMPRODUCT($C$13:$L$13/(1+$A48)^$C$14:$L$14)+$L$13*(1+F$46)/($A48-F$46)/(1+$A48)^$L$14+SUM($B$23:$B$29))/Inputs!$C$34*(1+$B$5)^$B$31-$B$32*$B$31)/Inputs!$C$36*100 -> 3346.7364
A49: =$B$9+0 -> 0.082461588 | B49: =((SUMPRODUCT($C$13:$L$13/(1+$A49)^$C$14:$L$14)+$L$13*(1+B$46)/($A49-B$46)/(1+$A49)^$L$14+SUM($B$23:$B$29))/Inputs!$C$34*(1+$B$5)^$B$31-$B$32*$B$31)/Inputs!$C$36*100 -> 2355.1266 | C49: =((SUMPRODUCT($C$13:$L$13/(1+$A49)^$C$14:$L$14)+$L$13*(1+C$46)/($A49-C$46)/(1+$A49)^$L$14+SUM($B$23:$B$29))/Inputs!$C$34*(1+$B$5)^$B$31-$B$32*$B$31)/Inputs!$C$36*100 -> 2478.9565 | D49: =((SUMPRODUCT($C$13:$L$13/(1+$A49)^$C$14:$L$14)+$L$13*(1+D$46)/($A49-D$46)/(1+$A49)^$L$14+SUM($B$23:$B$29))/Inputs!$C$34*(1+$B$5)^$B$31-$B$32*$B$31)/Inputs!$C$36*100 -> 2621.1419 | E49: =((SUMPRODUCT($C$13:$L$13/(1+$A49)^$C$14:$L$14)+$L$13*(1+E$46)/($A49-E$46)/(1+$A49)^$L$14+SUM($B$23:$B$29))/Inputs!$C$34*(1+$B$5)^$B$31-$B$32*$B$31)/Inputs!$C$36*100 -> 2786.0911 | F49: =((SUMPRODUCT($C$13:$L$13/(1+$A49)^$C$14:$L$14)+$L$13*(1+F$46)/($A49-F$46)/(1+$A49)^$L$14+SUM($B$23:$B$29))/Inputs!$C$34*(1+$B$5)^$B$31-$B$32*$B$31)/Inputs!$C$36*100 -> 2979.7463
A50: =$B$9+0.005 -> 0.087461588 | B50: =((SUMPRODUCT($C$13:$L$13/(1+$A50)^$C$14:$L$14)+$L$13*(1+B$46)/($A50-B$46)/(1+$A50)^$L$14+SUM($B$23:$B$29))/Inputs!$C$34*(1+$B$5)^$B$31-$B$32*$B$31)/Inputs!$C$36*100 -> 2152.4092 | C50: =((SUMPRODUCT($C$13:$L$13/(1+$A50)^$C$14:$L$14)+$L$13*(1+C$46)/($A50-C$46)/(1+$A50)^$L$14+SUM($B$23:$B$29))/Inputs!$C$34*(1+$B$5)^$B$31-$B$32*$B$31)/Inputs!$C$36*100 -> 2257.0424 | D50: =((SUMPRODUCT($C$13:$L$13/(1+$A50)^$C$14:$L$14)+$L$13*(1+D$46)/($A50-D$46)/(1+$A50)^$L$14+SUM($B$23:$B$29))/Inputs!$C$34*(1+$B$5)^$B$31-$B$32*$B$31)/Inputs!$C$36*100 -> 2376.1154 | E50: =((SUMPRODUCT($C$13:$L$13/(1+$A50)^$C$14:$L$14)+$L$13*(1+E$46)/($A50-E$46)/(1+$A50)^$L$14+SUM($B$23:$B$29))/Inputs!$C$34*(1+$B$5)^$B$31-$B$32*$B$31)/Inputs!$C$36*100 -> 2512.8389 | F50: =((SUMPRODUCT($C$13:$L$13/(1+$A50)^$C$14:$L$14)+$L$13*(1+F$46)/($A50-F$46)/(1+$A50)^$L$14+SUM($B$23:$B$29))/Inputs!$C$34*(1+$B$5)^$B$31-$B$32*$B$31)/Inputs!$C$36*100 -> 2671.4516
A51: =$B$9+0.01 -> 0.092461588 | B51: =((SUMPRODUCT($C$13:$L$13/(1+$A51)^$C$14:$L$14)+$L$13*(1+B$46)/($A51-B$46)/(1+$A51)^$L$14+SUM($B$23:$B$29))/Inputs!$C$34*(1+$B$5)^$B$31-$B$32*$B$31)/Inputs!$C$36*100 -> 1973.031 | C51: =((SUMPRODUCT($C$13:$L$13/(1+$A51)^$C$14:$L$14)+$L$13*(1+C$46)/($A51-C$46)/(1+$A51)^$L$14+SUM($B$23:$B$29))/Inputs!$C$34*(1+$B$5)^$B$31-$B$32*$B$31)/Inputs!$C$36*100 -> 2062.157 | D51: =((SUMPRODUCT($C$13:$L$13/(1+$A51)^$C$14:$L$14)+$L$13*(1+D$46)/($A51-D$46)/(1+$A51)^$L$14+SUM($B$23:$B$29))/Inputs!$C$34*(1+$B$5)^$B$31-$B$32*$B$31)/Inputs!$C$36*100 -> 2162.7888 | E51: =((SUMPRODUCT($C$13:$L$13/(1+$A51)^$C$14:$L$14)+$L$13*(1+E$46)/($A51-E$46)/(1+$A51)^$L$14+SUM($B$23:$B$29))/Inputs!$C$34*(1+$B$5)^$B$31-$B$32*$B$31)/Inputs!$C$36*100 -> 2277.3082 | F51: =((SUMPRODUCT($C$13:$L$13/(1+$A51)^$C$14:$L$14)+$L$13*(1+F$46)/($A51-F$46)/(1+$A51)^$L$14+SUM($B$23:$B$29))/Inputs!$C$34*(1+$B$5)^$B$31-$B$32*$B$31)/Inputs!$C$36*100 -> 2408.8032

Sheet LBO
A1: Carve-out LBO · Shell Marketing division
A2: USD millions. Division financials from Shell's FY2025 Form 20-F, note 7 (segment information). Sweep, revolver and interest on average balances are circular: iterative calculation is on.
A4: Operating base
A5: LTM revenue incl. inter-segment | B5: 119394
A6: LTM EBITDA (reported basis) | B6: 7902
A7: D&A excl. impairments, % revenue | B7: 0.019280701
A8: Capex, % revenue | B8: 0.015419535
A9: Working capital, % revenue (group proxy) | B9: 0.033883381
A10: Standalone costs, % revenue | B10: 0.004
A11: Tax rate | B11: 0.28
A12: Interest deductibility cap, % EBITDA | B12: 0.3
A13: Deal
A14: Entry EV / LTM EBITDA | B14: 7.5
A15: Exit EV / EBITDA | B15: 7.5
A16: Hold period (years) | B16: 5
A17: Advisory fees, % EV | B17: 0.01
A18: Separation costs, % EV | B18: 0.01
A19: Exit costs, % exit EV | B19: 0.01
A20: Minimum cash, % revenue | B20: 0.01
A21: Management promote, % of gain | B21: 0
A22: Financing
A23: Term loan B, x pro-forma EBITDA | B23: 3
A24: Senior notes, x | B24: 1.5
A25: Mezzanine, x | B25: 0.5
A26: Maximum debt, % of EV | B26: 0.7
A27: Base rate (US 13-week T-bill) | B27: 0.040500002
A28: TLB spread | B28: 0.035
A29: Notes coupon | B29: 0.075
A30: Mezzanine cash coupon | B30: 0.08
A31: Mezzanine PIK coupon | B31: 0.03
A32: Revolver commitment, x | B32: 0.75
A33: Revolver spread | B33: 0.03
A34: Undrawn fee | B34: 0.005
... A39: Circularity switch: 1 = average balances, 0 = opening | B39: 1
A41: Sources and uses
A42: Purchase price (EV) | B42: =$B$14*$B$6 -> 59265
A43: Pro-forma EBITDA (after standalone costs) | B43: =$B$6-$B$5*$B$10 -> 7424.424
A44: Debt scale factor (LTV cap) | B44: =MIN(1,$B$26*B42/(($B$23+$B$24+$B$25)*B43)) -> 1
A45: Term loan B | B45: =$B$23*B43*B44 -> 22273.272
A46: Senior notes | B46: =$B$24*B43*B44 -> 11136.636
A47: Mezzanine | B47: =$B$25*B43*B44 -> 3712.212
A48: Total debt | B48: =B45+B46+B47 -> 37122.12
A49: Revolver commitment (undrawn) | B49: =$B$32*B43 -> 5568.318
A50: Financing fees | B50: =$B$37*B48+0.01*B49 -> 890.93088
A51: Advisory fees | B51: =$B$17*B42 -> 592.65
A52: Separation costs | B52: =$B$18*B42 -> 592.65
A53: Cash to balance sheet | B53: =$B$20*$B$5 -> 1193.94
A54: Total uses | B54: =B42+B51+B50+B52+B53 -> 62535.171
A55: Sponsor equity | B55: =B54-B48 -> 25413.051
A57: Annual projection
B58: Close | C58: Year 1 | D58: Year 2 | E58: Year 3 | F58: Year 4 | G58: Year 5 | H58: Year 6 | I58: Year 7
A59: Revenue growth (input) | C59: 0 | D59: 0.01 | E59: 0.02 | F59: 0.02 | G59: 0.02 | H59: 0.02 | I59: 0.02
A60: EBITDA margin before standalone costs (input) | C60: 0.06618423 | D60: 0.06618423 | E60: 0.06618423 | F60: 0.06618423 | G60: 0.06618423 | H60: 0.06618423 | I60: 0.06618423
A61: Revenue | B61: =$B$5 -> 119394 | C61: =B61*(1+C59) -> 119394 | D61: =C61*(1+D59) -> 120587.94 | E61: =D61*(1+E59) -> 122999.7 | F61: =E61*(1+F59) -> 125459.69 | G61: =F61*(1+G59) -> 127968.89 | H61: =G61*(1+H59) -> 130528.26 | I61: =H61*(1+I59) -> 133138.83
A62: EBITDA (after standalone costs) | C62: =C61*(C60-$B$10) -> 7424.424 | D62: =D61*(D60-$B$10) -> 7498.6682 | E62: =E61*(E60-$B$10) -> 7648.6416 | F62: =F61*(F60-$B$10) -> 7801.6144 | G62: =G61*(G60-$B$10) -> 7957.6467 | H62: =H61*(H60-$B$10) -> 8116.7997 | I62: =I61*(I60-$B$10) -> 8279.1357
A63: D&A | C63: =C61*$B$7 -> 2302 | D63: =D61*$B$7 -> 2325.02 | E63: =E61*$B$7 -> 2371.5204 | F63: =F61*$B$7 -> 2418.9508 | G63: =G61*$B$7 -> 2467.3298 | H63: =H61*$B$7 -> 2516.6764 | I63: =I61*$B$7 -> 2567.0099
A64: EBIT | C64: =C62-C63 -> 5122.424 | D64: =D62-D63 -> 5173.6482 | E64: =E62-E63 -> 5277.1212 | F64: =F62-F63 -> 5382.6636 | G64: =G62-G63 -> 5490.3169 | H64: =H62-H63 -> 5600.1232 | I64: =I62-I63 -> 5712.1257
A65: Capex | C65: =C61*$B$8 -> 1841 | D65: =D61*$B$8 -> 1859.41 | E65: =E61*$B$8 -> 1896.5982 | F65: =F61*$B$8 -> 1934.5302 | G65: =G61*$B$8 -> 1973.2208 | H65: =H61*$B$8 -> 2012.6852 | I65: =I61*$B$8 -> 2052.9389
A66: Increase in working capital | C66: =$B$9*(C61-B61) -> 0 | D66: =$B$9*(D61-C61) -> 40.454724 | E66: =$B$9*(E61-D61) -> 81.718542 | F66: =$B$9*(F61-E61) -> 83.352913 | G66: =$B$9*(G61-F61) -> 85.019971 | H66: =$B$9*(H61-G61) -> 86.720371 | I66: =$B$9*(I61-H61) -> 88.454778
A67: Minimum cash | C67: =$B$20*C61 -> 1193.94 | D67: =$B$20*D61 -> 1205.8794 | E67: =$B$20*E61 -> 1229.997 | F67: =$B$20*F61 -> 1254.5969 | G67: =$B$20*G61 -> 1279.6889 | H67: =$B$20*H61 -> 1305.2826 | I67: =$B$20*I61 -> 1331.3883
A68: Mandatory TLB amortisation | C68: =MIN(B87,$B$35*$B$45) -> 222.73272 | D68: =MIN(C87,$B$35*$B$45) -> 222.73272 | E68: =MIN(D87,$B$35*$B$45) -> 222.73272 | F68: =MIN(E87,$B$35*$B$45) -> 222.73272 | G68: =MIN(F87,$B$35*$B$45) -> 222.73272 | H68: =MIN(G87,$B$35*$B$45) -> 222.73272 | I68: =MIN(H87,$B$35*$B$45) -> 222.73272
A69: Revolver interest + undrawn fee | C69: =IFERROR(($B$27+$B$33)*IF($B$39=1,(B86+C86)/2,B86)+$B$34*MAX($B$49-IF($B$39=1,(B86+C86)/2,B86),0),0) -> 27.84159 | D69: =IFERROR(($B$27+$B$33)*IF($B$39=1,(C86+D86)/2,C86)+$B$34*MAX($B$49-IF($B$39=1,(C86+D86)/2,C86),0),0) -> 27.84159 | E69: =IFERROR(($B$27+$B$33)*IF($B$39=1,(D86+E86)/2,D86)+$B$34*MAX($B$49-IF($B$39=1,(D86+E86)/2,D86),0),0) -> 27.84159 | F69: =IFERROR(($B$27+$B$33)*IF($B$39=1,(E86+F86)/2,E86)+$B$34*MAX($B$49-IF($B$39=1,(E86+F86)/2,E86),0),0) -> 27.84159 | G69: =IFERROR(($B$27+$B$33)*IF($B$39=1,(F86+G86)/2,F86)+$B$34*MAX($B$49-IF($B$39=1,(F86+G86)/2,F86),0),0) -> 27.84159 | H69: =IFERROR(($B$27+$B$33)*IF($B$39=1,(G86+H86)/2,G86)+$B$34*MAX($B$49-IF($B$39=1,(G86+H86)/2,G86),0),0) -> 27.84159 | I69: =IFERROR(($B$27+$B$33)*IF($B$39=1,(H86+I86)/2,H86)+$B$34*MAX($B$49-IF($B$39=1,(H86+I86)/2,H86),0),0) -> 27.84159
A70: TLB interest | C70: =IFERROR(($B$27+$B$28)*IF($B$39=1,(B87+C87)/2,B87),0) -> 1604.2104 | D70: =IFERROR(($B$27+$B$28)*IF($B$39=1,(C87+D87)/2,C87),0) -> 1443.8167 | E70: =IFERROR(($B$27+$B$28)*IF($B$39=1,(D87+E87)/2,D87),0) -> 1270.0116 | F70: =IFERROR(($B$27+$B$28)*IF($B$39=1,(E87+F87)/2,E87),0) -> 1077.7807 | G70: =IFERROR(($B$27+$B$28)*IF($B$39=1,(F87+G87)/2,F87),0) -> 864.81658 | H70: =IFERROR(($B$27+$B$28)*IF($B$39=1,(G87+H87)/2,G87),0) -> 632.29833 | I70: =IFERROR(($B$27+$B$28)*IF($B$39=1,(H87+I87)/2,H87),0) -> 380.42305
A71: Notes interest | C71: =$B$29*B88 -> 835.2477 | D71: =$B$29*C88 -> 835.2477 | E71: =$B$29*D88 -> 835.2477 | F71: =$B$29*E88 -> 835.2477 | G71: =$B$29*F88 -> 835.2477 | H71: =$B$29*G88 -> 835.2477 | I71: =$B$29*H88 -> 835.2477
A72: Mezzanine cash interest | C72: =$B$30*B89 -> 296.97696 | D72: =$B$30*C89 -> 305.88627 | E72: =$B$30*D89 -> 315.06286 | F72: =$B$30*E89 -> 324.51474 | G72: =$B$30*F89 -> 334.25018 | H72: =$B$30*G89 -> 344.27769 | I72: =$B$30*H89 -> 354.60602
A73: Mezzanine PIK accrual | C73: =$B$31*B89 -> 111.36636 | D73: =$B$31*C89 -> 114.70735 | E73: =$B$31*D89 -> 118.14857 | F73: =$B$31*E89 -> 121.69303 | G73: =$B$31*F89 -> 125.34382 | H73: =$B$31*G89 -> 129.10413 | I73: =$B$31*H89 -> 132.97726
A74: Interest income on cash | C74: =IFERROR(MAX($B$27-0.005,0)*IF($B$39=1,(B85+C85)/2,B85),0) -> 42.384872 | D74: =IFERROR(MAX($B$27-0.005,0)*IF($B$39=1,(C85+D85)/2,C85),0) -> 42.596797 | E74: =IFERROR(MAX($B$27-0.005,0)*IF($B$39=1,(D85+E85)/2,D85),0) -> 43.236808 | F74: =IFERROR(MAX($B$27-0.005,0)*IF($B$39=1,(E85+F85)/2,E85),0) -> 44.101544 | G74: =IFERROR(MAX($B$27-0.005,0)*IF($B$39=1,(F85+G85)/2,F85),0) -> 44.983575 | H74: =IFERROR(MAX($B$27-0.005,0)*IF($B$39=1,(G85+H85)/2,G85),0) -> 45.883247 | I74: =IFERROR(MAX($B$27-0.005,0)*IF($B$39=1,(H85+I85)/2,H85),0) -> 46.800912
A75: Net cash interest | C75: =C69+C70+C71+C72-C74 -> 2721.8918 | D75: =D69+D70+D71+D72-D74 -> 2570.1954 | E75: =E69+E70+E71+E72-E74 -> 2404.927 | F75: =F69+F70+F71+F72-F74 -> 2221.2832 | G75: =G69+G70+G71+G72-G74 -> 2017.1725 | H75: =H69+H70+H71+H72-H74 -> 1793.7821 | I75: =I69+I70+I71+I72-I74 -> 1551.3174
A76: Net interest incl. PIK and fee amortisation | C76: =C69+C70+C71+C72+C73+$B$50/$B$38-C74 -> 2960.534 | D76: =D69+D70+D71+D72+D73+$B$50/$B$38-D74 -> 2812.1786 | E76: =E69+E70+E71+E72+E73+$B$50/$B$38-E74 -> 2650.3514 | F76: =F69+F70+F71+F72+F73+$B$50/$B$38-F74 -> 2470.252 | G76: =G69+G70+G71+G72+G73+$B$50/$B$38-G74 -> 2269.7921 | H76: =H69+H70+H71+H72+H73+$B$50/$B$38-H74 -> 2050.162 | I76: =I69+I70+I71+I72+I73+$B$50/$B$38-I74 -> 1811.5705
A77: Deductible interest (capped) | C77: =MIN(C76,MAX($B$12*C62,0)) -> 2227.3272 | D77: =MIN(D76,MAX($B$12*D62,0)) -> 2249.6005 | E77: =MIN(E76,MAX($B$12*E62,0)) -> 2294.5925 | F77: =MIN(F76,MAX($B$12*F62,0)) -> 2340.4843 | G77: =MIN(G76,MAX($B$12*G62,0)) -> 2269.7921 | H77: =MIN(H76,MAX($B$12*H62,0)) -> 2050.162 | I77: =MIN(I76,MAX($B$12*I62,0)) -> 1811.5705
A78: Cash tax | C78: =$B$11*MAX(C64-C77,0) -> 810.6271 | D78: =$B$11*MAX(D64-D77,0) -> 818.73338 | E78: =$B$11*MAX(E64-E77,0) -> 835.10804 | F78: =$B$11*MAX(F64-F77,0) -> 851.8102 | G78: =$B$11*MAX(G64-G77,0) -> 901.74693 | H78: =$B$11*MAX(H64-H77,0) -> 993.98914 | I78: =$B$11*MAX(I64-I77,0) -> 1092.1554
A79: Cash flow before debt service | C79: =C62-C78-C65-C66 -> 4772.7969 | D79: =D62-D78-D65-D66 -> 4780.0701 | E79: =E62-E78-E65-E66 -> 4835.2168 | F79: =F62-F78-F65-F66 -> 4931.9212 | G79: =G62-G78-G65-G66 -> 4997.6591 | H79: =H62-H78-H65-H66 -> 5023.405 | I79: =I62-I78-I65-I66 -> 5045.5865
A80: Cash available above the floor | C80: =B85+C79-C75-C68-C67 -> 1828.1724 | D80: =C85+D79-D75-D68-D67 -> 1975.2026 | E80: =D85+E79-E75-E68-E67 -> 2183.4396 | F80: =E85+F79-F75-F68-F67 -> 2463.3053 | G80: =F85+G79-G75-G68-G67 -> 2732.6619 | H80: =G85+H79-H75-H68-H67 -> 2981.2964 | I80: =H85+I79-I75-I68-I67 -> 3245.4307
A81: Revolver drawn | C81: =MIN(MAX(-C80,0),MAX($B$49-B86,0)) -> 0 | D81: =MIN(MAX(-D80,0),MAX($B$49-C86,0)) -> 0 | E81: =MIN(MAX(-E80,0),MAX($B$49-D86,0)) -> 0 | F81: =MIN(MAX(-F80,0),MAX($B$49-E86,0)) -> 0 | G81: =MIN(MAX(-G80,0),MAX($B$49-F86,0)) -> 0 | H81: =MIN(MAX(-H80,0),MAX($B$49-G86,0)) -> 0 | I81: =MIN(MAX(-I80,0),MAX($B$49-H86,0)) -> 0
A82: Revolver repaid | C82: =MIN(B86,MAX(C80,0)) -> 0 | D82: =MIN(C86,MAX(D80,0)) -> 0 | E82: =MIN(D86,MAX(E80,0)) -> 0 | F82: =MIN(E86,MAX(F80,0)) -> 0 | G82: =MIN(F86,MAX(G80,0)) -> 0 | H82: =MIN(G86,MAX(H80,0)) -> 0 | I82: =MIN(H86,MAX(I80,0)) -> 0
A83: Cash sweep to TLB | C83: =$B$36*MIN(B87-C68,MAX(C80-C82,0)) -> 1828.1724 | D83: =$B$36*MIN(C87-D68,MAX(D80-D82,0)) -> 1975.2026 | E83: =$B$36*MIN(D87-E68,MAX(E80-E82,0)) -> 2183.4396 | F83: =$B$36*MIN(E87-F68,MAX(F80-F82,0)) -> 2463.3053 | G83: =$B$36*MIN(F87-G68,MAX(G80-G82,0)) -> 2732.6619 | H83: =$B$36*MIN(G87-H68,MAX(H80-H82,0)) -> 2981.2964 | I83: =$B$36*MIN(H87-I68,MAX(I80-I82,0)) -> 3245.4307
A84: Free cash flow after interest | C84: =C79-C75 -> 2050.9051 | D84: =D79-D75 -> 2209.8747 | E84: =E79-E75 -> 2430.2899 | F84: =F79-F75 -> 2710.638 | G84: =G79-G75 -> 2980.4866 | H84: =H79-H75 -> 3229.6229 | I84: =I79-I75 -> 3494.2691
A85: Cash | B85: =B53 -> 1193.94 | C85: =B85+C79-C75-C68+C81-C82-C83 -> 1193.94 | D85: =C85+D79-D75-D68+D81-D82-D83 -> 1205.8794 | E85: =D85+E79-E75-E68+E81-E82-E83 -> 1229.997 | F85: =E85+F79-F75-F68+F81-F82-F83 -> 1254.5969 | G85: =F85+G79-G75-G68+G81-G82-G83 -> 1279.6889 | H85: =G85+H79-H75-H68+H81-H82-H83 -> 1305.2826 | I85: =H85+I79-I75-I68+I81-I82-I83 -> 1331.3883
A86: Revolver | B86: 0 | C86: =B86+C81-C82 -> 0 | D86: =C86+D81-D82 -> 0 | E86: =D86+E81-E82 -> 0 | F86: =E86+F81-F82 -> 0 | G86: =F86+G81-G82 -> 0 | H86: =G86+H81-H82 -> 0 | I86: =H86+I81-I82 -> 0
A87: Term loan B | B87: =B45 -> 22273.272 | C87: =B87-C68-C83 -> 20222.367 | D87: =C87-D68-D83 -> 18024.432 | E87: =D87-E68-E83 -> 15618.259 | F87: =E87-F68-F83 -> 12932.221 | G87: =F87-G68-G83 -> 9976.8266 | H87: =G87-H68-H83 -> 6772.7975 | I87: =H87-I68-I83 -> 3304.634
A88: Senior notes | B88: =B46 -> 11136.636 | C88: =B88 -> 11136.636 | D88: =C88 -> 11136.636 | E88: =D88 -> 11136.636 | F88: =E88 -> 11136.636 | G88: =F88 -> 11136.636 | H88: =G88 -> 11136.636 | I88: =H88 -> 11136.636
A89: Mezzanine (with PIK) | B89: =B47 -> 3712.212 | C89: =B89+C73 -> 3823.5784 | D89: =C89+D73 -> 3938.2857 | E89: =D89+E73 -> 4056.4343 | F89: =E89+F73 -> 4178.1273 | G89: =F89+G73 -> 4303.4711 | H89: =G89+H73 -> 4432.5753 | I89: =H89+I73 -> 4565.5525
A90: Total debt | B90: =B86+B87+B88+B89 -> 37122.12 | C90: =C86+C87+C88+C89 -> 35182.581 | D90: =D86+D87+D88+D89 -> 33099.353 | E90: =E86+E87+E88+E89 -> 30811.33 | F90: =F86+F87+F88+F89 -> 28246.985 | G90: =G86+G87+G88+G89 -> 25416.934 | H90: =H86+H87+H88+H89 -> 22342.009 | I90: =I86+I87+I88+I89 -> 19006.823
A91: Net debt | B91: =B90-B85 -> 35928.18 | C91: =C90-C85 -> 33988.641 | D91: =D90-D85 -> 31893.474 | E91: =E90-E85 -> 29581.333 | F91: =F90-F85 -> 26992.388 | G91: =G90-G85 -> 24137.245 | H91: =H90-H85 -> 21036.726 | I91: =I90-I85 -> 17675.434
A92: Debt / EBITDA | C92: =IF(C62>0,C90/C62,0) -> 4.7387624 | D92: =IF(D62>0,D90/D62,0) -> 4.4140309 | E92: =IF(E62>0,E90/E62,0) -> 4.0283401 | F92: =IF(F62>0,F90/F62,0) -> 3.6206589 | G92: =IF(G62>0,G90/G62,0) -> 3.1940264 | H92: =IF(H62>0,H90/H62,0) -> 2.7525638 | I92: =IF(I62>0,I90/I62,0) -> 2.2957496
A93: EBITDA / net cash interest | C93: =IF(C75>0,C62/C75,0) -> 2.7276705 | D93: =IF(D75>0,D62/D75,0) -> 2.9175479 | E93: =IF(E75>0,E62/E75,0) -> 3.180405 | F93: =IF(F75>0,F62/F75,0) -> 3.5122107 | G93: =IF(G75>0,G62/G75,0) -> 3.9449511 | H93: =IF(H75>0,H62/H75,0) -> 4.5249642 | I93: =IF(I75>0,I62/I75,0) -> 5.3368417
A95: Returns at exit
A96: Exit EV = exit multiple × EBITDA in the exit year | B96: =$B$15*INDEX($C$62:$I$62,$B$16) -> 59682.35
A97: Net debt at exit | B97: =INDEX($C$91:$I$91,$B$16) -> 24137.245
A98: Exit costs | B98: =$B$19*B96 -> 596.8235
A99: Equity before promote | B99: =B96-B97-B98 -> 34948.282
A100: Management promote | B100: =MAX(B99-$B$55,0)*$B$21 -> 0
A101: Sponsor equity at exit | B101: =B99-B100 -> 34948.282
A102: Money multiple (MOIC) | B102: =B101/$B$55 -> 1.37521
A103: IRR | B103: =IF(B102>0,B102^(1/$B$16)-1,-1) -> 0.065795311

Sheet Merger
A1: Shell acquires BP · deal terms, purchase accounting and EPS
A2: USD millions. Terms and accounting are live formulas. Standalone and pro forma net income come from the Python engine (the full pro forma forecast is in model/ma.py) and are marked as such.
A4: Market data
A5: Shell share price (GBp) | B5: 3836
A6: Shell shares (m) | B6: 5691.4747
A7: BP share price (GBp) | B7: 588
A8: BP shares (m) | B8: 15453.549
A9: GBP/USD | B9: 1.3207946
A10: Terms
A11: Premium to BP share price | B11: 0.3
A12: Paid in Shell shares | B12: 0.5
A13: Advisory fees, % target EV | B13: 0.003
A14: Financing fees, % acquisition debt | B14: 0.01
A15: Cash consideration funded from cash (USD m) | B15: 0
A16: BP divested, % of EBITDA | B16: 0
A17: Divestment EV/EBITDA | B17: 6
A18: Fair-value uplift on BP fixed assets | B18: 0.08
A19: Deferred tax rate on uplift | B19: 0.25
A20: Uplift depreciation life (years) | B20: 15
A21: BP at close, 31 Dec 2026 (Python standalone forecast)
A22: Equity attributable to shareholders | B22: 51768.904
A23: Goodwill | B23: 10300
A24: Fixed assets | B24: 105335.1
A25: Borrowings + revolver | B25: 57958
A26: Lease liabilities | B26: 14571
A27: Cash | B27: 36684.504
A28: Minorities (incl. hybrids) | B28: 20948
A29: EBITDA 2026 | B29: 36655.089
A31: Consideration, funding and ownership
A32: BP market capitalisation | B32: =$B$8*$B$7/100*$B$9 -> 120016.47
A33: Equity purchase price | B33: =B32*(1+$B$11) -> 156021.41
A34: Offer per BP share (GBp) | B34: =$B$7*(1+$B$11) -> 764.4
A35: Paid in new Shell shares | B35: =B33*$B$12 -> 78010.703
A36: Paid in cash | B36: =B33-B35 -> 78010.703
A37: New Shell shares issued (m) | B37: =B35/($B$5/100*$B$9) -> 1539.7149
A38: Pro forma shares (m) | B38: =$B$6+B37 -> 7231.1896
A39: BP holders' ownership | B39: =B37/B38 -> 0.21292692
A40: BP net debt incl. leases | B40: =$B$25+$B$26-$B$27 -> 35844.496
A41: Target enterprise value (price + net debt + minorities) | B41: =B33+B40+$B$28 -> 212813.9
A42: Advisory fees | B42: =$B$13*B41 -> 638.4417
A43: Divestment proceeds | B43: =$B$17*$B$16*$B$29 -> 0
A44: Acquisition debt (grossed up for its own fee) | B44: =MAX((B36+B42-$B$15-B43)/(1-$B$14),0) -> 79443.58
A45: Financing fees | B45: =$B$14*B44 -> 794.4358
A47: Purchase price allocation (IFRS 3)
A48: Fair-value uplift | B48: =$B$18*$B$24*(1-$B$16) -> 8426.808
A49: Deferred tax on uplift | B49: =B48*$B$19 -> 2106.702
A50: Fair value of net assets acquired | B50: =$B$22-$B$23+B48-B49 -> 47789.01
A51: Goodwill created | B51: =B33-B50 -> 108232.4
A52: Annual step-up depreciation | B52: =B48/$B$20 -> 561.7872
A54: EPS accretion (net income from the Python engine; per-share maths live)
B55: 2027E | C55: 2028E | D55: 2029E | E55: 2030E | F55: 2031E
A56: Shell standalone net income to shareholders (Python) | B56: 18103.932 | C56: 18713.365 | D56: 19338.223 | E56: 19979.631 | F56: 20617.13
A57: Pro forma net income to shareholders (Python) | B57: 23709.689 | C57: 25699.616 | D57: 28703.251 | E57: 30087.937 | F57: 31390.5
A58: Shell standalone EPS (USD) | B58: =B56/$B$6 -> 3.180886 | C58: =C56/$B$6 -> 3.2879641 | D58: =D56/$B$6 -> 3.3977526 | E58: =E56/$B$6 -> 3.5104489 | F58: =F56/$B$6 -> 3.6224584
A59: Pro forma EPS (USD) | B59: =B57/$B$38 -> 3.2788089 | C59: =C57/$B$38 -> 3.5539955 | D59: =D57/$B$38 -> 3.9693678 | E59: =E57/$B$38 -> 4.1608557 | F59: =F57/$B$38 -> 4.340987
A60: Accretion / (dilution) | B60: =B59/B58-1 -> 0.030784776 | C60: =C59/C58-1 -> 0.080910673 | D60: =D59/D58-1 -> 0.16823331 | E60: =E59/E58-1 -> 0.18527739 | F60: =F59/F58-1 -> 0.19835387

Sheet Portfolio
A1: Portfolio · 13 assets in GBP
A2: Annualised, from weekly GBP returns since Jan 2021 (Yahoo Finance adjusted closes). Covariance is Ledoit-Wolf shrunk. Weights come from the Python optimiser (it cannot be expressed as formulas); edit any weight and the statistics recalculate.
A4: Inputs
A5: Risk-free rate | B5: 0.040500002
A6: Equity risk premium (CAPM prior) | B6: 0.05
A7: Weight on history in expected returns | B7: 0.25
A9: Asset | B9: Hist. mean | C9: Beta | D9: Exp. return | E9: Max Sharpe | F9: Min variance | G9: Risk parity | H9: Max diversification | I9: Equal weight
A10: Barclays | B10: 0.22788475 | C10: 1.573361 | D10: =$B$7*B10+(1-$B$7)*($B$5+C10*$B$6) -> 0.14634723 | E10: 0.082172572 | F10: 0.0062407812 | G10: 0.056399564 | H10: 0.015734505 | I10: 0.076923077
A11: Prudential | B11: -0.028946613 | C11: 1.4358786 | D11: =$B$7*B11+(1-$B$7)*($B$5+C11*$B$6) -> 0.076983796 | E11: 0 | F11: 0 | G11: 0.05434188 | H11: 0.019923888 | I11: 0.076923077
A12: Rolls-Royce | B12: 0.51335462 | C12: 1.2617923 | D12: =$B$7*B12+(1-$B$7)*($B$5+C12*$B$6) -> 0.20603087 | E12: 0.21010406 | F12: 0.045896112 | G12: 0.059600768 | H12: 0.088908062 | I12: 0.076923077
A13: Glencore | B13: 0.18269406 | C13: 1.331847 | D13: =$B$7*B13+(1-$B$7)*($B$5+C13*$B$6) -> 0.12599278 | E13: 0.10695193 | F13: 0.062253066 | G13: 0.066878034 | H13: 0.10171685 | I13: 0.076923077
A14: SSE | B14: 0.10298106 | C14: 0.77479947 | D14: =$B$7*B14+(1-$B$7)*($B$5+C14*$B$6) -> 0.085175246 | E14: 0.035828815 | F14: 0.031144737 | G14: 0.07640227 | H14: 0.045927863 | I14: 0.076923077
A15: United Utilities | B15: 0.09487951 | C15: 0.52892053 | D15: =$B$7*B15+(1-$B$7)*($B$5+C15*$B$6) -> 0.073929399 | E15: 0.077798111 | F15: 0.14458941 | G15: 0.095826396 | H15: 0.11215206 | I15: 0.076923077
A16: BT | B16: 0.10072851 | C16: 0.87416857 | D16: =$B$7*B16+(1-$B$7)*($B$5+C16*$B$6) -> 0.088338451 | E16: 1.8566109e-17 | F16: 0.014405352 | G16: 0.06261473 | H16: 0.059129019 | I16: 0.076923077
A17: British American Tobacco | B17: 0.095154607 | C17: 0.63700814 | D17: =$B$7*B17+(1-$B$7)*($B$5+C17*$B$6) -> 0.078051458 | E17: 0.069676987 | F17: 0.12277188 | G17: 0.10018535 | H17: 0.13259578 | I17: 0.076923077
A18: AstraZeneca | B18: 0.1098184 | C18: 0.94103547 | D18: =$B$7*B18+(1-$B$7)*($B$5+C18*$B$6) -> 0.093118431 | E18: 0.078390933 | F18: 0.070065984 | G18: 0.087346327 | H18: 0.090023417 | I18: 0.076923077
A19: Palantir | B19: 0.58290943 | C19: 0.63472303 | D19: =$B$7*B19+(1-$B$7)*($B$5+C19*$B$6) -> 0.19990447 | E19: 0.072580529 | F19: 0.016887751 | G19: 0.043187958 | H19: 0.072163415 | I19: 0.076923077
A20: Coca-Cola | B20: 0.14358825 | C20: 0.42019088 | D20: =$B$7*B20+(1-$B$7)*($B$5+C20*$B$6) -> 0.082029222 | E20: 0.25 | F20: 0.24871097 | G20: 0.12998784 | H20: 0.1748181 | I20: 0.076923077
A21: Equinix | B21: 0.12456443 | C21: 0.47375468 | D21: =$B$7*B21+(1-$B$7)*($B$5+C21*$B$6) -> 0.079281909 | E21: 0.016496064 | F21: 0.059598054 | G21: 0.079990739 | H21: 0.077736274 | I21: 0.076923077
A22: EEMA | B22: 0.073548998 | C22: 0.68936491 | D22: =$B$7*B22+(1-$B$7)*($B$5+C22*$B$6) -> 0.074613435 | E22: 2.5033862e-17 | F22: 0.17743591 | G22: 0.087238139 | H22: 0.0091707707 | I22: 0.076923077
A23: Sum of weights | E23: =SUM(E10:E22) -> 1 | F23: =SUM(F10:F22) -> 1 | G23: =SUM(G10:G22) -> 1 | H23: =SUM(H10:H22) -> 1 | I23: =SUM(I10:I22) -> 1
A25: Annual covariance matrix (Ledoit-Wolf)
B26: Barclays | C26: Prudential | D26: Rolls-Royce | E26: Glencore | F26: SSE | G26: United Utilities | H26: BT | I26: British American Tobacco | J26: AstraZeneca | K26: Palantir | L26: Coca-Cola | M26: Equinix | N26: EEMA
A27: Barclays | B27: 0.090884375 | C27: 0.041341857 | D27: 0.042273441 | E27: 0.028933813 | F27: 0.0086916697 | G27: 0.003917644 | H27: 0.016942914 | I27: 0.01040297 | J27: 0.0054881265 | K27: 0.023749145 | L27: 0.0020746216 | M27: 0.0064490699 | N27: 0.019002771
A28: Prudential | B28: 0.041341857 | C28: 0.090557435 | D28: 0.031934093 | E28: 0.033199627 | F28: 0.010369645 | G28: 0.0093611827 | H28: 0.023441673 | I28: 0.0067482221 | J28: 0.0068170346 | K28: 0.011307217 | L28: 0.003976102 | M28: 0.0071232468 | N28: 0.025841037
A29: Rolls-Royce | B29: 0.042273441 | C29: 0.031934093 | D29: 0.13823808 | E29: 0.018527042 | F29: 0.002759167 | G29: 0.00075906317 | H29: 0.016994579 | I29: -0.00044808444 | J29: 0.010201913 | K29: 0.023928598 | L29: -0.0012793075 | M29: -0.0024089227 | N29: 0.016458597
A30: Glencore | B30: 0.028933813 | C30: 0.033199627 | D30: 0.018527042 | E30: 0.10362511 | F30: 0.0109657 | G30: 0.00061274349 | H30: 0.0070008773 | I30: 0.00026681621 | J30: 0.0087171512 | K30: 0.013023005 | L30: -0.0021030594 | M30: 0.0081636368 | N30: 0.01625788
A31: SSE | B31: 0.0086916697 | C31: 0.010369645 | D31: 0.002759167 | E31: 0.0109657 | F31: 0.059398243 | G31: 0.023266328 | H31: 0.015667271 | I31: 0.0084047919 | J31: 0.015216712 | K31: -0.0088823823 | L31: 0.0089159525 | M31: 0.013825272 | N31: 0.0024352353
A32: United Utilities | B32: 0.003917644 | C32: 0.0093611827 | D32: 0.00075906317 | E32: 0.00061274349 | F32: 0.023266328 | G32: 0.044159698 | H32: 0.018005553 | I32: 0.0062652581 | J32: 0.0093654865 | K32: -0.0061143065 | L32: 0.0071807884 | M32: 0.0098883277 | N32: 0.0031606047
A33: BT | B33: 0.016942914 | C33: 0.023441673 | D33: 0.016994579 | E33: 0.0070008773 | F33: 0.015667271 | G33: 0.018005553 | H33: 0.097051292 | I33: 0.016576418 | J33: 0.0080292609 | K33: 0.0018677834 | L33: 0.005806476 | M33: 0.0044981637 | N33: 0.0088613001
A34: British American Tobacco | B34: 0.01040297 | C34: 0.0067482221 | D34: -0.00044808444 | E34: 0.00026681621 | F34: 0.0084047919 | G34: 0.0062652581 | H34: 0.016576418 | I34: 0.052292317 | J34: 0.0098647504 | K34: -0.0097500065 | L34: 0.012486869 | M34: 0.00042112319 | N34: 0.0010150448
A35: AstraZeneca | B35: 0.0054881265 | C35: 0.0068170346 | D35: 0.010201913 | E35: 0.0087171512 | F35: 0.015216712 | G35: 0.0093654865 | H35: 0.0080292609 | I35: 0.0098647504 | J35: 0.057325872 | K35: -0.011455994 | L35: 0.0099294876 | M35: 0.007582757 | N35: 0.004395997
A36: Palantir | B36: 0.023749145 | C36: 0.011307217 | D36: 0.023928598 | E36: 0.013023005 | F36: -0.0088823823 | G36: -0.0061143065 | H36: 0.0018677834 | I36: -0.0097500065 | J36: -0.011455994 | K36: 0.43631594 | L36: -0.011702028 | M36: 0.042508707 | N36: 0.032742027
A37: Coca-Cola | B37: 0.0020746216 | C37: 0.003976102 | D37: -0.0012793075 | E37: -0.0021030594 | F37: 0.0089159525 | G37: 0.0071807884 | H37: 0.005806476 | I37: 0.012486869 | J37: 0.0099294876 | K37: -0.011702028 | L37: 0.029939542 | M37: 0.0069200559 | N37: 0.0034489641
A38: Equinix | B38: 0.0064490699 | C38: 0.0071232468 | D38: -0.0024089227 | E38: 0.0081636368 | F38: 0.013825272 | G38: 0.0098883277 | H38: 0.0044981637 | I38: 0.00042112319 | J38: 0.007582757 | K38: 0.042508707 | L38: 0.0069200559 | M38: 0.065952258 | N38: 0.013576664
A39: EEMA | B39: 0.019002771 | C39: 0.025841037 | D39: 0.016458597 | E39: 0.01625788 | F39: 0.0024352353 | G39: 0.0031606047 | H39: 0.0088613001 | I39: 0.0010150448 | J39: 0.004395997 | K39: 0.032742027 | L39: 0.0034489641 | M39: 0.013576664 | N39: 0.036777427
A41: Weights as rows (for w′Σw)
A42: Max Sharpe | B42: =E10 -> 0.082172572 | C42: =E11 -> 0 | D42: =E12 -> 0.21010406 | E42: =E13 -> 0.10695193 | F42: =E14 -> 0.035828815 | G42: =E15 -> 0.077798111 | H42: =E16 -> 1.8566109e-17 | I42: =E17 -> 0.069676987 | J42: =E18 -> 0.078390933 | K42: =E19 -> 0.072580529 | L42: =E20 -> 0.25 | M42: =E21 -> 0.016496064 | N42: =E22 -> 2.5033862e-17
A43: Min variance | B43: =F10 -> 0.0062407812 | C43: =F11 -> 0 | D43: =F12 -> 0.045896112 | E43: =F13 -> 0.062253066 | F43: =F14 -> 0.031144737 | G43: =F15 -> 0.14458941 | H43: =F16 -> 0.014405352 | I43: =F17 -> 0.12277188 | J43: =F18 -> 0.070065984 | K43: =F19 -> 0.016887751 | L43: =F20 -> 0.24871097 | M43: =F21 -> 0.059598054 | N43: =F22 -> 0.17743591
A44: Risk parity | B44: =G10 -> 0.056399564 | C44: =G11 -> 0.05434188 | D44: =G12 -> 0.059600768 | E44: =G13 -> 0.066878034 | F44: =G14 -> 0.07640227 | G44: =G15 -> 0.095826396 | H44: =G16 -> 0.06261473 | I44: =G17 -> 0.10018535 | J44: =G18 -> 0.087346327 | K44: =G19 -> 0.043187958 | L44: =G20 -> 0.12998784 | M44: =G21 -> 0.079990739 | N44: =G22 -> 0.087238139
A45: Max diversification | B45: =H10 -> 0.015734505 | C45: =H11 -> 0.019923888 | D45: =H12 -> 0.088908062 | E45: =H13 -> 0.10171685 | F45: =H14 -> 0.045927863 | G45: =H15 -> 0.11215206 | H45: =H16 -> 0.059129019 | I45: =H17 -> 0.13259578 | J45: =H18 -> 0.090023417 | K45: =H19 -> 0.072163415 | L45: =H20 -> 0.1748181 | M45: =H21 -> 0.077736274 | N45: =H22 -> 0.0091707707
A46: Equal weight | B46: =I10 -> 0.076923077 | C46: =I11 -> 0.076923077 | D46: =I12 -> 0.076923077 | E46: =I13 -> 0.076923077 | F46: =I14 -> 0.076923077 | G46: =I15 -> 0.076923077 | H46: =I16 -> 0.076923077 | I46: =I17 -> 0.076923077 | J46: =I18 -> 0.076923077 | K46: =I19 -> 0.076923077 | L46: =I20 -> 0.076923077 | M46: =I21 -> 0.076923077 | N46: =I22 -> 0.076923077
A48: Portfolio statistics
B49: Exp. return | C49: Volatility | D49: Sharpe | E49: Beta
A50: Max Sharpe | B50: =SUMPRODUCT($E$10:$E$22,$D$10:$D$22) -> 0.12665446 | C50: =SQRT(SUMPRODUCT($B$27:$N$39*($E$10:$E$22*$B$42:$N$42))) -> 0.1382397 | D50: =(B50-$B$5)/C50 -> 0.62322518 | E50: =SUMPRODUCT($E$10:$E$22,$C$10:$C$22) -> 0.88283236
A51: Min variance | B51: =SUMPRODUCT($F$10:$F$22,$D$10:$D$22) -> 0.090676102 | C51: =SQRT(SUMPRODUCT($B$27:$N$39*($F$10:$F$22*$B$43:$N$43))) -> 0.10828065 | D51: =(B51-$B$5)/C51 -> 0.46338934 | E51: =SUMPRODUCT($F$10:$F$22,$C$10:$C$22) -> 0.67376119
A52: Risk parity | B52: =SUMPRODUCT($G$10:$G$22,$D$10:$D$22) -> 0.10036676 | C52: =SQRT(SUMPRODUCT($B$27:$N$39*($G$10:$G$22*$B$44:$N$44))) -> 0.11777317 | D52: =(B52-$B$5)/C52 -> 0.50832254 | E52: =SUMPRODUCT($G$10:$G$22,$C$10:$C$22) -> 0.821739
A53: Max diversification | B53: =SUMPRODUCT($H$10:$H$22,$D$10:$D$22) -> 0.10674199 | C53: =SQRT(SUMPRODUCT($B$27:$N$39*($H$10:$H$22*$B$45:$N$45))) -> 0.11994171 | D53: =(B53-$B$5)/C53 -> 0.55228481 | E53: =SUMPRODUCT($H$10:$H$22,$C$10:$C$22) -> 0.77920277
A54: Equal weight | B54: =SUMPRODUCT($I$10:$I$22,$D$10:$D$22) -> 0.1084459 | C54: =SQRT(SUMPRODUCT($B$27:$N$39*($I$10:$I$22*$B$46:$N$46))) -> 0.13159324 | D54: =(B54-$B$5)/C54 -> 0.51633272 | E54: =SUMPRODUCT($I$10:$I$22,$C$10:$C$22) -> 0.8905265

Sheet Checks
A1: Checks · workbook vs Python engine
A2: Each line compares a live Excel result with the Python engine. Tolerances are absolute.
A4: Check | B4: Excel | C4: Python | D4: Difference | E4: Tolerance | F4: Status
A5: History balances (max abs, FY2021–25) | B5: =MAX(ABS(History!B46),ABS(History!C46),ABS(History!D46),ABS(History!E46),ABS(History!F46)) -> 0 | C5: 0 | D5: =B5-C5 -> 0 | E5: 0.5 | F5: =IFERROR(IF(ABS(D5)<=E5,"PASS","FAIL"),"ERROR") -> PASS
A6: Forecast balance sheet balances (max abs) | B6: =MAX(Forecast!B54:'Forecast'!L54,-MIN(Forecast!B54:'Forecast'!L54)) -> 0 | C6: 0 | D6: =B6-C6 -> 0 | E6: 0.01 | F6: =IFERROR(IF(ABS(D6)<=E6,"PASS","FAIL"),"ERROR") -> PASS
A7: Revenue 2035 | B7: =Forecast!L6 -> 308095.63 | C7: 308095.63 | D7: =B7-C7 -> 0 | E7: 0.01 | F7: =IFERROR(IF(ABS(D7)<=E7,"PASS","FAIL"),"ERROR") -> PASS
A8: Net income 2026 | B8: =Forecast!C15 -> 17911.643 | C8: 17911.643 | D8: =B8-C8 -> 0 | E8: 0.01 | F8: =IFERROR(IF(ABS(D8)<=E8,"PASS","FAIL"),"ERROR") -> PASS
A9: Closing cash 2030 | B9: =Forecast!G41 -> 25487.391 | C9: 25487.391 | D9: =B9-C9 -> 0 | E9: 0.01 | F9: =IFERROR(IF(ABS(D9)<=E9,"PASS","FAIL"),"ERROR") -> PASS
A10: Buybacks 2028 | B10: =Forecast!E35 -> 5849.5696 | C10: 5849.5696 | D10: =B10-C10 -> -1.4551915e-11 | E10: 0.01 | F10: =IFERROR(IF(ABS(D10)<=E10,"PASS","FAIL"),"ERROR") -> PASS
A11: Unlevered FCF 2035 | B11: =Forecast!L57 -> 19076.616 | C11: 19076.616 | D11: =B11-C11 -> 0 | E11: 0.01 | F11: =IFERROR(IF(ABS(D11)<=E11,"PASS","FAIL"),"ERROR") -> PASS
A12: WACC | B12: =DCF!B9 -> 0.082461588 | C12: 0.082461588 | D12: =B12-C12 -> 0 | E12: 1e-09 | F12: =IFERROR(IF(ABS(D12)<=E12,"PASS","FAIL"),"ERROR") -> PASS
A13: Enterprise value | B13: =DCF!B22 -> 253060.71 | C13: 253060.71 | D13: =B13-C13 -> 0 | E13: 0.05 | F13: =IFERROR(IF(ABS(D13)<=E13,"PASS","FAIL"),"ERROR") -> PASS
A14: Equity value | B14: =DCF!B30 -> 189884.96 | C14: 189884.96 | D14: =B14-C14 -> 0 | E14: 0.05 | F14: =IFERROR(IF(ABS(D14)<=E14,"PASS","FAIL"),"ERROR") -> PASS
A15: DCF value per share (pence) | B15: =DCF!B34 -> 2621.1419 | C15: 2621.1419 | D15: =B15-C15 -> 0 | E15: 0.01 | F15: =IFERROR(IF(ABS(D15)<=E15,"PASS","FAIL"),"ERROR") -> PASS
A16: Exit-multiple value per share (pence) | B16: =DCF!B43 -> 2607.1469 | C16: 2607.1469 | D16: =B16-C16 -> 0 | E16: 0.01 | F16: =IFERROR(IF(ABS(D16)<=E16,"PASS","FAIL"),"ERROR") -> PASS
A17: Sensitivity grid centre = point estimate | B17: =DCF!D49 -> 2621.1419 | C17: 2621.1419 | D17: =B17-C17 -> 0 | E17: 0.01 | F17: =IFERROR(IF(ABS(D17)<=E17,"PASS","FAIL"),"ERROR") -> PASS
A18: Interest expense 2027 | B18: =Forecast!D10 -> 4671 | C18: 4671 | D18: =B18-C18 -> 0 | E18: 0.01 | F18: =IFERROR(IF(ABS(D18)<=E18,"PASS","FAIL"),"ERROR") -> PASS
A19: Shareholders' equity 2035 | B19: =Forecast!L51 -> 195159.27 | C19: 195159.27 | D19: =B19-C19 -> 0 | E19: 0.01 | F19: =IFERROR(IF(ABS(D19)<=E19,"PASS","FAIL"),"ERROR") -> PASS
A20: LBO sponsor equity | B20: =LBO!B55 -> 25413.051 | C20: 25413.051 | D20: =B20-C20 -> 0 | E20: 0.01 | F20: =IFERROR(IF(ABS(D20)<=E20,"PASS","FAIL"),"ERROR") -> PASS
A21: LBO cash interest, year 1 | B21: =LBO!C75 -> 2721.8918 | C21: 2721.8918 | D21: =B21-C21 -> -3.1923264e-10 | E21: 0.01 | F21: =IFERROR(IF(ABS(D21)<=E21,"PASS","FAIL"),"ERROR") -> PASS
A22: LBO term loan B after year 5 | B22: =LBO!G87 -> 9976.8266 | C22: 9976.8266 | D22: =B22-C22 -> -2.5975169e-09 | E22: 0.01 | F22: =IFERROR(IF(ABS(D22)<=E22,"PASS","FAIL"),"ERROR") -> PASS
A23: LBO IRR | B23: =LBO!B103 -> 0.065795311 | C23: 0.065795311 | D23: =B23-C23 -> 1.5987212e-14 | E23: 1e-06 | F23: =IFERROR(IF(ABS(D23)<=E23,"PASS","FAIL"),"ERROR") -> PASS
A24: LBO MOIC | B24: =LBO!B102 -> 1.37521 | C24: 1.37521 | D24: =B24-C24 -> 1.0236256e-13 | E24: 1e-06 | F24: =IFERROR(IF(ABS(D24)<=E24,"PASS","FAIL"),"ERROR") -> PASS
A25: Merger: equity purchase price | B25: =Merger!B33 -> 156021.41 | C25: 156021.41 | D25: =B25-C25 -> 0 | E25: 0.01 | F25: =IFERROR(IF(ABS(D25)<=E25,"PASS","FAIL"),"ERROR") -> PASS
A26: Merger: acquisition debt | B26: =Merger!B44 -> 79443.58 | C26: 79443.58 | D26: =B26-C26 -> 0 | E26: 0.01 | F26: =IFERROR(IF(ABS(D26)<=E26,"PASS","FAIL"),"ERROR") -> PASS
A27: Merger: BP holders' ownership | B27: =Merger!B39 -> 0.21292692 | C27: 0.21292692 | D27: =B27-C27 -> 0 | E27: 1e-09 | F27: =IFERROR(IF(ABS(D27)<=E27,"PASS","FAIL"),"ERROR") -> PASS
A28: Merger: goodwill created | B28: =Merger!B51 -> 108232.4 | C28: 108232.4 | D28: =B28-C28 -> 0 | E28: 0.01 | F28: =IFERROR(IF(ABS(D28)<=E28,"PASS","FAIL"),"ERROR") -> PASS
A29: Merger: EPS accretion 2029 | B29: =Merger!D60 -> 0.16823331 | C29: 0.16823331 | D29: =B29-C29 -> 0 | E29: 1e-06 | F29: =IFERROR(IF(ABS(D29)<=E29,"PASS","FAIL"),"ERROR") -> PASS
A30: Portfolio volatility · Max Sharpe | B30: =Portfolio!C50 -> 0.1382397 | C30: 0.1382397 | D30: =B30-C30 -> 0 | E30: 1e-08 | F30: =IFERROR(IF(ABS(D30)<=E30,"PASS","FAIL"),"ERROR") -> PASS
A31: Portfolio expected return · Max Sharpe | B31: =Portfolio!B50 -> 0.12665446 | C31: 0.12665446 | D31: =B31-C31 -> 0 | E31: 1e-08 | F31: =IFERROR(IF(ABS(D31)<=E31,"PASS","FAIL"),"ERROR") -> PASS
A32: Portfolio volatility · Min variance | B32: =Portfolio!C51 -> 0.10828065 | C32: 0.10828065 | D32: =B32-C32 -> 0 | E32: 1e-08 | F32: =IFERROR(IF(ABS(D32)<=E32,"PASS","FAIL"),"ERROR") -> PASS
A33: Portfolio expected return · Min variance | B33: =Portfolio!B51 -> 0.090676102 | C33: 0.090676102 | D33: =B33-C33 -> 0 | E33: 1e-08 | F33: =IFERROR(IF(ABS(D33)<=E33,"PASS","FAIL"),"ERROR") -> PASS
A34: Portfolio volatility · Risk parity | B34: =Portfolio!C52 -> 0.11777317 | C34: 0.11777317 | D34: =B34-C34 -> 0 | E34: 1e-08 | F34: =IFERROR(IF(ABS(D34)<=E34,"PASS","FAIL"),"ERROR") -> PASS
A35: Portfolio expected return · Risk parity | B35: =Portfolio!B52 -> 0.10036676 | C35: 0.10036676 | D35: =B35-C35 -> 0 | E35: 1e-08 | F35: =IFERROR(IF(ABS(D35)<=E35,"PASS","FAIL"),"ERROR") -> PASS
A36: Portfolio volatility · Max diversification | B36: =Portfolio!C53 -> 0.11994171 | C36: 0.11994171 | D36: =B36-C36 -> 0 | E36: 1e-08 | F36: =IFERROR(IF(ABS(D36)<=E36,"PASS","FAIL"),"ERROR") -> PASS
A37: Portfolio expected return · Max diversification | B37: =Portfolio!B53 -> 0.10674199 | C37: 0.10674199 | D37: =B37-C37 -> 0 | E37: 1e-08 | F37: =IFERROR(IF(ABS(D37)<=E37,"PASS","FAIL"),"ERROR") -> PASS
A38: Portfolio volatility · Equal weight | B38: =Portfolio!C54 -> 0.13159324 | C38: 0.13159324 | D38: =B38-C38 -> 0 | E38: 1e-08 | F38: =IFERROR(IF(ABS(D38)<=E38,"PASS","FAIL"),"ERROR") -> PASS
A39: Portfolio expected return · Equal weight | B39: =Portfolio!B54 -> 0.1084459 | C39: 0.1084459 | D39: =B39-C39 -> 0 | E39: 1e-08 | F39: =IFERROR(IF(ABS(D39)<=E39,"PASS","FAIL"),"ERROR") -> PASS
A40: Portfolio weights sum to 100% (max abs error) | B40: =MAX(ABS(Portfolio!E23-1),ABS(Portfolio!F23-1),ABS(Portfolio!G23-1),ABS(Portfolio!H23-1),ABS(Portfolio!I23-1)) -> 2.220446e-16 | C40: 0 | D40: =B40-C40 -> 2.220446e-16 | E40: 1e-06 | F40: =IFERROR(IF(ABS(D40)<=E40,"PASS","FAIL"),"ERROR") -> PASS
A42: Overall | F42: =IF(COUNTIF(F5:F40,"PASS")=ROWS(F5:F40),"ALL PASS",ROWS(F5:F40)-COUNTIF(F5:F40,"PASS")&" NOT PASSING") -> ALL PASS

Sheet History
A1: Shell plc · reported history
A2: USD millions. Source: Shell plc Form 20-F, FY2021–FY2025, XBRL facts via SEC EDGAR (https://data.sec.gov/api/xbrl/companyfacts/CIK0001306965.json). Derived lines are noted.
A4: Line item (USD m) | B4: 2021 | C4: 2022 | D4: 2023 | E4: 2024 | F4: 2025
A5: Revenue | B5: 261504 | C5: 381314 | D5: 316620 | E5: 284312 | F5: 266886
A6: Profit before tax | B6: 29829 | C6: 64815 | D6: 32627 | E6: 29922 | F6: 29756
A7: Taxation | B7: 9199 | C7: 21941 | D7: 12991 | E7: 13401 | F7: 11637
A8: Net income | B8: 20630 | C8: 42874 | D8: 19636 | E8: 16521 | F8: 18119
A9: Net income to shareholders | B9: 20101 | C9: 42309 | D9: 19359 | E9: 16094 | F9: 17837
A10: D&A incl. impairments (cash-flow add-back) | B10: 26921 | C10: 18529 | D10: 31290 | E10: 26872 | F10: 25299
A11: Interest expense | B11: 3607 | C11: 3181 | D11: 4673 | E11: 4787 | F11: 4671
A12: Cash from operations | B12: 45104 | C12: 68414 | D12: 54191 | E12: 54687 | F12: 42863
A13: Cash from investing | B13: -4761 | C13: -22448 | D13: -17734 | E13: -15155 | F13: -16811
A14: Cash from financing | B14: -34664 | C14: -41954 | D14: -38235 | E14: -38435 | F14: -35812
A15: Capital expenditure | B15: 19000 | C15: 22600 | D15: 22993 | E15: 19601 | F15: 18947
A16: Dividends paid | B16: 6669 | C16: 7489 | D16: 9153 | E16: 8976 | F16: 8619
... A44: Operating EBIT, ex JV and finance items (derived) | B44: 22283 | C44: 63109 | D44: 30737 | E44: 29992 | F44: 27582
A46: Balance check: total assets − total liabilities − total equity | B46: =B18-B26-B32 -> 0 | C46: =C18-C26-C32 -> 0 | D46: =D18-D26-D32 -> 0 | E46: =E18-E26-E32 -> 0 | F46: =F18-F26-F32 -> 0
